{
  "type": "悬疑脑洞",
  "date": "2026-06-12",
  "prev_date": "2026-06-07",
  "category": {
    "name": "悬疑脑洞",
    "trend": {
      "new_count": 29,
      "dropped_count": 19,
      "new_books": [
        "你好诡异Boss，我是来打工的",
        "不要在无限流里招惹精神病！",
        "宿舍求生：开局加入诡异管理群",
        "全民躲猫猫：疯批美人她满级天眼",
        "规则怪谈：王子总是对我垂涎欲滴"
      ],
      "dropped_books": [
        {
          "title": "盗墓：你们偷我家小麒麟？",
          "intro": "（评分刚出，会涨，主角万人迷，目前暂定有cp） 吳谓被倒霉系统绑错穿越到了盗墓世界，收集盗墓世界中的非正常能量。 明明选的是根正苗红的张家麒麟血，却阴差阳错被吳家捡回去养了十几年。 本想藏好血脉，跟着"
        },
        {
          "title": "什么变态，那是我老公",
          "intro": "明想嫁给谢均，结婚两年，生活平淡且幸福。 可这一天，她突然看到了出现的弹幕。 【笑死，女配不会以为她会很幸福吧，嫁给了一个变态杀人狂魔】 【都不知道自己怎么死的，还在那沾沾自喜】 明想：胡说，我老公怎"
        },
        {
          "title": "盗墓笔记：原来是故人没死",
          "intro": "［评分刚出，会涨］【张家麒麟女+cp张起灵+战斗力天花板+天授失忆】 苦中作乐花孔雀×失忆寻妻小苦瓜 张家末代族长和族长夫人，为何落得对面人不识？ 为何麒麟女苦苦躲藏数年？ ———————— 狗五爷："
        },
        {
          "title": "盗墓：开局给小花推销乾坤袋",
          "intro": "【all女主】 沈玉汐绑定了一个修真系统，正准备穿到修真界开启爽文人生，然而穿越中途系统能量耗尽，她被丢到了1998年的盗墓世界。 没有钱，还是个黑户，她只好凭借半吊子的修真技能努力抱大腿。 抱着抱着"
        },
        {
          "title": "漂亮小可怜在暗黑童话被疯狂觊觎",
          "intro": "【暗黑童话+万人迷+女嬷向+1vN+男全洁】 【暗黑向，含墙制，球禁等】 【非女强非大女主，妹宝柔弱爱哭还胆小】 ... 下面是简介：诡异游戏降临，人类需要通关才可生存。 而云姝，一个漂亮的不像话的柔"
        }
      ],
      "top_risers": [],
      "top_fallers": [
        {
          "title": "盗笔：我真不是张家人，真的！",
          "change": "-7"
        }
      ],
      "reads_growth": [
        {
          "title": "盗笔：我真不是张家人，真的！",
          "growth": "+8000"
        }
      ],
      "summary": "新增29本上榜；19本掉出（《盗墓：你们偷我家小麒麟？》、《什么变态，那是我老公》、《盗墓笔记：原来是故人没死》、《盗墓：开局给小花推销乾坤袋》、《漂亮小可怜在暗黑童话被疯狂觊觎》）；《盗笔：我真不是张家人，真的！》阅读量+8000。"
    },
    "books": [
      {
        "title": "你好诡异Boss，我是来打工的",
        "author": "七一子",
        "reads": "31.8万",
        "intro": "【实体出版已签约】 【女频无CP无限流+剧情流+微惊悚】 失业第一天，黎雾手机上莫名多了一个APP。 上面的工作简单且高薪，一看就是杀猪盘。 黎雾：“去！去的就是杀猪盘。” 她的工作任务很简单： 【小女孩保姆——5000元/天】 【整形医院护士——10000/天】 【农村守村人——30000/天】 工作内容透明，工资日结，杀猪盘她也认了。 …… 入职保姆第一天，小女孩死了。 黎雾：“建议公司赔偿烧纸钱。” 入职护士俩小时，不小心被人爆了头。 黎雾：“希望保险管管这事。” 成为守村人的夜晚，村子烧起来了。 黎雾：“受工伤的话建议三倍赔偿。” 别人都在工作中抱头鼠窜尖叫哭嚎之际，黎雾早已默默成为了优秀员工，名字牢牢挂在榜一。 她的留言受全员工瞻仰： “人钱九九。”",
        "cover": "https://p3-reading-sign.fqnovelpic.com/novel-pic/75d653a64683d66c61a50d7f3e955814~tplv-resize:225:0.image?lk3s=5b7047ff&x-expires=1781853736&x-signature=AFUFjmL%2FAQWGETCynLE8ZEM4lko%3D",
        "url": "https://fanqienovel.com/page/7542165189974576190"
      },
      {
        "title": "不要在无限流里招惹精神病！",
        "author": "灼云客",
        "reads": "24.6万",
        "intro": "【无限流+爽文+团队热血群像+微解密+惊悚逃生】 【顶级天赋·能文能武·冷幽默大女主，和她各显其能的队友们】 起初那些变态观众们以为，某个穿病号服的可怜女人，在第一局就要惨死夜里。 直到他们亲眼见证，她哼着小曲，游刃有余，以一己之力坑杀全局竞争者，人气引爆了直播间。 “疯子！这就是个不折不扣的疯子啊！” “她好帅，我好爱！” 温柔神性的假面被撕碎，蛰伏的凶兽露出獠牙。 是盗贼，是杀手，天赋超绝的鬼才，无所畏惧的斗士。 这场厄运游戏，终于迎来了新的主宰。 —————— 阅读须知： 1.女主经常装疯卖傻逗别人玩，实际上是绝对强者，团队核心，不存在女强男更强； 2.没有完美性格，也没有绝对道德，尤其是女主，她随心所欲； 3.无固定感情线，团队关系好，所有人都爱女主（任何层面的爱）； 4.团队男女成员均有，核心三位都是女性，男性也各具特色，大家会穿插进入副本； 5.直播间存在各种奇葩观众，会产生低级言论，有吵架对立的情况； 6.本文纯架空背景，私设众多，与现实毫无关联，请勿过度考究，或者自我代入； 7.创作自由，一切为剧情和角色服务，遣词造句我会自行斟酌，拒绝任何形式的写作指导。",
        "cover": "https://p3-reading-sign.fqnovelpic.com/novel-pic/p2oee0b715bbc12c5b4bdff8b34dfc75260~tplv-resize:225:0.image?lk3s=5b7047ff&x-expires=1781853736&x-signature=uKa5L5Utuik%2FPT5tHPdDMi0tMSI%3D",
        "url": "https://fanqienovel.com/page/7592919783155190808"
      },
      {
        "title": "宿舍求生：开局加入诡异管理群",
        "author": "27sui",
        "reads": "17.6万",
        "intro": "【无CP+爽文+塔防+诡异+求生+大佬】 　　江浸月在即将签署家人《手术知情同意书》的下一秒，眼前一黑被拉入宿舍求生游戏。 　　夜晚七点一到，门外开始出现恐怖的诡异，它们在走廊上游荡，时刻准备破门而入。 　　活下去的唯一方法就是升级宿舍大门，升级武器炮台，开门抢夺宝箱。 　　永冻深林、幽灵诡船、规则怪谈、欲望赌场、太平医院…… 　　江浸月手握【管理群】游走在诡异与玩家之间，售卖消息，抢占先机，坑蒙拐骗，只为活着回去。 　　无CP女强爽文，大多数是女角色，欢迎入坑，绝不憋屈！\\( ͯω ͯ)/",
        "cover": "https://p3-reading-sign.fqnovelpic.com/novel-pic/p2odff36b7896a104958353d0a38b2bbf5c~tplv-resize:225:0.image?lk3s=5b7047ff&x-expires=1781853736&x-signature=QXXTrX15EFaNHk%2Bvq3YaC1naxYI%3D",
        "url": "https://fanqienovel.com/page/7623619349001014334"
      },
      {
        "title": "全民躲猫猫：疯批美人她满级天眼",
        "author": "油炸雪梨",
        "reads": "15.7万",
        "intro": "【评分刚开，会涨的】【游戏入侵+躲猫猫+直播+女主+无CP】 核战之后，蓝星已成焦土，躲猫猫是人类唯一的希望。 全球躲猫猫游戏降临，被选中的人将代表国家出战，胜则抽取奖励，败则领土沦陷！ 当龙国第四十四轮参赛者林岁安出现时，弹幕哀嚎： “穿病号服？踩着拖鞋？完了，龙国气运已尽！” 然而，当其他选手躲在柜子里瑟瑟发抖时，林岁安在诡异眼皮子底下吃小蛋糕； 当小鬼子被诡异镰刀腰斩时，林岁安在窗外卡BUG逗诡异玩。 全世界都疯了：“让你去和诡异躲猫猫，你在这儿当自家后花园呢？” 林岁安拎着刚抢来的神秘道具，歪头一笑：“不好意思，精神病院住久了，看谁都像好人。” ----- 【排雷：1.没那么惊悚；2.私设，诡异不是中式诡异，均为改造形态；3.文中有鬼魂，但不是诡异。】",
        "cover": "https://p3-reading-sign.fqnovelpic.com/novel-pic/p2oa938b4c249ce755b0dd05758b3cc9ea2~tplv-resize:225:0.image?lk3s=5b7047ff&x-expires=1781853736&x-signature=ghDa%2BzCW%2Fw8MAAcmqqn2SJIjw5s%3D",
        "url": "https://fanqienovel.com/page/7615645509008493593"
      },
      {
        "title": "规则怪谈：王子总是对我垂涎欲滴",
        "author": "总有青葱",
        "reads": "15.5万",
        "intro": "【已签出版】【短剧漫剧已上线】 【无cp➕无限流➕惊悚游戏➕无国运➕暗黑童话】 妙龄少女在午夜低声哭泣 英俊潇洒的王子在夜晚变成嗜血“野兽” 灰姑娘惨死在舞会当夜 惊悚游戏被裹上玻璃糖纸，伪装成甜蜜的糖果。美好的童话世界背后，究竟隐藏着什么…… —— 怪谈降临地球，全球人口在一个月内骤减20亿。 　　图南被怪谈选中，抽签怪谈分类的时候，她赌上了自己全部的运气。 　　“叮咚！恭喜您抽中童话分类，您的运气真是无与伦比。作为整个怪谈世界最梦幻最安全的怪谈，童话世界绝对是您居家旅行出行必备的不二之选！” 　　请牢记童话世界的绝对守则： 　　作为童话人物，请牢记你的人设！ 　 　　最后，欢迎您来到童话世界！ 　　美人鱼、灰姑娘、豌豆公主…… 等等……这个长着一张嘴的童话书又是什么东西？ 会有惊悚诡异的元素，胆子特别小的慎入～ 内含多种元素，不单纯为规则怪谈，部分副本规则存在感极弱",
        "cover": "https://p3-reading-sign.fqnovelpic.com/novel-pic/5c74a50bc0362f2b0bd339c18e09223e~tplv-resize:225:0.image?lk3s=5b7047ff&x-expires=1781853736&x-signature=o5unF3rFWxieR0qQ%2FT9OtSJoqPU%3D",
        "url": "https://fanqienovel.com/page/7400699192022158361"
      },
      {
        "title": "我还能在规则怪谈里塌房不成？",
        "author": "喜杳",
        "reads": "15万",
        "intro": "【无限流+规则怪谈+惊悚游戏+女强团队+集体脑子不正常】 出道前夕，时厘所在的组合惨遭队友背刺，背上了霸凌黑锅。 出道失败，队友美美赢得了网友的怜爱，重新出道风生水起，时厘的社交帐号至今还被对方的脑残粉们团建追骂。 好巧不巧，被公司雪藏的第三年，惊悚降临。 【坐标：蓝星，惊悚国运战场已过审。】 【正在随机抽取本次惊悚乐园的主题——】 【叮！本次主题为……KPOP爱豆团体！】 …… 【爱豆生存指南】 （蛋糕的烛火熄灭，你将只剩下登顶这一条生路，为了你的生命安全，请务必遵守以下规则：） 【一、爱豆为贩卖幻想的职业，任何恋爱行为将视为偶像失格。】 【二、宿舍并非绝对安全，若发现私生潜入的痕迹，请及时反锁房间的门窗……但万一，它就藏身在你的房间里面呢？】 【三、时刻遵守爱豆的职业素养，请拒绝以下行为：签售会切小屏，私联粉丝，舞台划水……】 【四、在粉丝面前时刻保持团魂，没有团魂的组合是一盘散沙，哪怕装……也要装得体面。】",
        "cover": "https://p3-reading-sign.fqnovelpic.com/novel-pic/p2oef36e9704ab627a868e2c04199450612~tplv-resize:225:0.image?lk3s=5b7047ff&x-expires=1781853736&x-signature=sM81m7bid60BxrhOSeFlqMdlmHI%3D",
        "url": "https://fanqienovel.com/page/7358402657045711896"
      },
      {
        "title": "惊悚游戏：从萝莉开始无限逃生",
        "author": "咸鱼五二",
        "reads": "12.3万",
        "intro": "【无限流+无cp+惊悚游戏+成长型女主+微群像】 一张特殊的卡片，引领身处绝境的人，进入无限惊悚游戏…… 活下去，就有机会获得数之不尽的财富，成为人上人。 活不下去，就会成为各种怨灵的养料，在离开游戏后莫名其妙死亡。 你，做好进入游戏的准备了吗？ —— 没有准备好也没有关系，你没有选择的余地。 欢迎进入惊悚游戏，花槐。",
        "cover": "https://p3-reading-sign.fqnovelpic.com/novel-pic/p2oe8ada7be06970049d33cbe39fc60549a~tplv-resize:225:0.image?lk3s=5b7047ff&x-expires=1781853736&x-signature=7Fvz2AF0bpN%2FKY6CMJTNqJVopLw%3D",
        "url": "https://fanqienovel.com/page/7441088503900818494"
      },
      {
        "title": "在恐怖游戏里谈的恋爱千奇百怪",
        "author": "奔跑的桃子",
        "reads": "11.3万",
        "intro": "白瑶成了诸多恐怖世界里空有美貌，且满身铜臭味的恶毒女配。 系统给她抛下“攻略”两个字后就因为信号不好失联了。 她看过那么多小说，很懂套路，不就是要她去攻略有悲惨遭遇的男人吗？ 她在看到某人的第一眼时，能察觉对方身上出现的暗红色光芒，她猜那一定就是自己的攻略对象，于是—— 在闹鬼的寄宿制校园里，她捡到了被人欺负的单纯少年，她给他补课，给他送花，与他躲在死过人的美术室里偷偷的搂搂抱抱。 在六人逃生的废弃医院，她救下了被所有人视为累赘而丢下的病弱少年，她给他送资源，给他送装备，与他藏在衣柜里小心的亲吻。 在危机遍布的海岛，看到那坨黑色带着触手的形似章鱼的生物，她也来者不拒，把黑色怪物藏在了自己的口袋里，它一天天长大，最后有了人的形状，她觉得可以教它亲吻了。 系统重新上线，失声惊叫，“你究竟是怎么能做到和那么多鬼怪BOSS谈恋爱的啊！” 白瑶:“你不是说让我攻略他们？” 系统崩溃，“我是让你把游戏攻略成功活到最后，没有叫你嫖BOSS 啊！” 白瑶:“啊这……” 不可言说的怪物身体撕成两半，它的触手把藏起来的贝壳都送到了她的面前，“瑶瑶，亲我呀。” 白瑶:好感度都刷满了，不亲说的过去？",
        "cover": "https://p3-reading-sign.fqnovelpic.com/novel-pic/p2o2c27e0bb82d6b5ba94bfb4942e8d542c~tplv-resize:225:0.image?lk3s=5b7047ff&x-expires=1781853736&x-signature=5OHu3bRfSEtHOTEemF8SwAkt%2Fr0%3D",
        "url": "https://fanqienovel.com/page/7250087472565062656"
      },
      {
        "title": "国运怪谈，我让纯情男鬼多子多福",
        "author": "卿城之墨",
        "reads": "10.3万",
        "intro": "【评分刚出，后面会涨的】【规则怪谈+多子多福+男全洁+国运+爽文+直播+生存】 “放肆！不知廉耻！” 沈修竹被按在棺材里时，红透了耳根，声音颤抖得像个受惊的雏儿。 他是杀人不眨眼的S级厉鬼，却被林软心一个“平地摔”抱大腿喊相公搞得CPU烧毁。 林软心：哎呀，系统说你欲望值100，你装什么清高呢？（挑眉） 这就是林软心的日常：在规则怪谈里撩最凶的鬼，生最强的娃。 别国选手：救命！鬼医生拿手术刀过来了！ 林软心：白医生，我心口疼，你摸摸看是不是缺个女朋友？（无辜眨眼） 结果：白医生手抖了，心动了，龙国寿命涨了，雪花画面又亮了。 她不仅是在逃生，她是在治愈这些病娇、阴湿、傲娇的男鬼们。 “软心，只要你别看别人，命都给你。” 面对28个顶级男神的病娇占有欲，林软心表示：我只是想救国，不是想腰折啊！",
        "cover": "https://p3-reading-sign.fqnovelpic.com/novel-pic/p2o06642b11742f9d1d5e838aa7beb1c792~tplv-resize:225:0.image?lk3s=5b7047ff&x-expires=1781853736&x-signature=J0bEdGabsiGB5glgK2lufVKeqCQ%3D",
        "url": "https://fanqienovel.com/page/7613722976994724889"
      },
      {
        "title": "状元她在恐怖游戏杀疯了",
        "author": "吃饭第一名咋了",
        "reads": "9.5万",
        "intro": "评分刚开，后面会涨 【无限流+惊悚游戏+烧脑悬疑+无cp】 季遥，理科省状元，重度游戏宅，带着她那随时会宕机的身体穿进惊悚游戏。 全网直播间都在等这个粉色头发的“脆皮花瓶”暴毙，赌她活不过三秒。 直到—— 规则杀人，她冷笑一声，讽刺副本逻辑漏洞比女娲补天的窟窿还大。 怪物索命，她头也不回，直接被猫主子驮着提前三秒站在生路尽头。 终焉降临，她双眼赤红，嘶吼既然万物并非偶然那我便能算出一切。 观众从鄙夷、崩溃，到彻底被圈粉。 别人在挣扎尖叫，季遥在刷分通关。 在这场名为「寒武纪」的残酷进化中， 她是唯一的生存变量，也是游戏的终结真神。 ——·——·—— 阅读须知： 1.暗黑叙事·人性剖析·部分情节掉San预警 2.没有重生/系统，脑子就是最强外挂！",
        "cover": "https://p3-reading-sign.fqnovelpic.com/novel-pic/p2o2f48d6698cc111520e3b9ba3e030da7f~tplv-resize:225:0.image?lk3s=5b7047ff&x-expires=1781853736&x-signature=8fxVPQz7i5Jf2PhuAxRzfBAj69M%3D",
        "url": "https://fanqienovel.com/page/7533610495371136024"
      },
      {
        "title": "盗笔：我真不是张家人，真的！",
        "author": "想要发财的富贵",
        "reads": "9.5万",
        "intro": "【刚出分，后续会涨。无cp，人物私设原著土著。有回忆杀很多，非爽文。不是吴邪黑！不黑主角团！简介无力。有点火葬场和日常文的特色】 张安没有想到只是一个姓，会给他的人生带来天翻地覆的变化。 他和一个叫关根的初遇，因为他藏着右手，他就问他是不是张家人。 张安摇头，他不知道什么是张家人，藏着右手当然是有他的原因。 后来，他遇到了很多人，他们都把他当成了张家人，无论张安怎么解释，他们都不相信。 张安没招了，一个装睡的人是永远叫不醒的，更何况是这么多装睡的人。 于是他成了吴邪计划里的第一个棋子，也是后来计划里十七个少年中唯一“死”掉的那个。 张安在长白山崖迎来了新生，只是没想到一场意外让他们重逢。 他们都以为人死了，没想到在雨村他们又相遇了。 …… 吴邪看着“沈姑姑”作画的背影，想起门后那幅旧画。 王胖子隔着墨镜，再也看不见“沈祖祖”眼里曾如月牙弯起的笑意。 黑瞎子看着他戴的墨镜，一度怀疑这是影分身。 张起灵沉默注视，他认得那双眼睛，却不懂族人为何否认自己的身份。 黎簇拽住他的衣袖，声音发颤：“小安哥，我没家了，你也不要我了吗？” 张安坐在悬崖边，心想他要回家了，这些人又唱又跳的干什么。",
        "cover": "https://p3-reading-sign.fqnovelpic.com/novel-pic/p2o0ce462149e7cd6a8d5239e57ac02f8d2~tplv-resize:225:0.image?lk3s=5b7047ff&x-expires=1781853740&x-signature=38r5LF7sOqWfSoTH4Ck5ENkGhYI%3D",
        "url": "https://fanqienovel.com/page/7618255935110138905"
      },
      {
        "title": "盗笔：大佬？不，是死的太多",
        "author": "映河山",
        "reads": "8.2万",
        "intro": "已恢复更新 虚拟古墓，盗笔同人，无cp，美强惨，主角一个人扮演了整个家族 主角性别为男 谢淮安一朝穿进盗墓笔记，唯一的金手指就是一个随身古墓。 你以为这个古墓很厉害？ 不，它只能模拟各种古墓现场，并让你体验花样死法。 下斗高手？Nonono，他只是在模拟空间里死的太多。 看起来模样不大的清冷少年身上散发着淡淡死气？你死那么多次也可以。 设定：随身古墓可以现场模拟机关，主角不是牛逼，是同一个机关死了太多次，随身古墓内随时读档重来，空间内与正常时间流速不同。 排雷： 双男主标签我以为是俩主角都是男的，不知道要有爱情才能打，但签约后不能更改标签了，所以再次声明非爱情向，原著没有的cp这里不包分配哈。 前期小谢因为穷，没有开痛感屏蔽，这个接受不了的宝宝避一下雷哈。",
        "cover": "https://p3-reading-sign.fqnovelpic.com/novel-pic/p2o85449042a2087e0e91a6aafb0e78830d~tplv-resize:225:0.image?lk3s=5b7047ff&x-expires=1781853740&x-signature=ajGNTQDvFAw%2FF3rqRnDvR13DNyk%3D",
        "url": "https://fanqienovel.com/page/7466117635466333209"
      },
      {
        "title": "国运：扮演张麒麟，我是女版小哥",
        "author": "离殊公子",
        "reads": "7.9万",
        "intro": "女频！女频！女频！ 【爽文+真假千金+原创剧情+直播+绝不原谅+全家火葬场＋无cp】 墨琦琳（音同墨麒麟）穿越到另一个世界的自己身上，另一个世界的自己，是被保姆掉包的豪门真千金，爸爸不疼，妈妈不爱，哥哥弟弟更是极尽嘲讽苛待，只把假千金宠上了天！ 假千金还是朵黑心莲，会演戏，会算计，不但让另一个世界的自己成为全家黑，甚至还成为全豪门黑，全国黑！ 最后，另一个世界的自己在新郎抱着假千金，从婚礼现场离开后，绝望的跳楼而死。 墨琦琳穿越过来，发誓一定要为另一个世界的自己报仇。 只是正当她思索如何报仇的时候，国运降临，她和假千金，以及视她为耻辱的父母、哥哥弟弟们都被国运选中。 国运世界危险重重，一不留神就会丢了性命，幸运的是，墨琦琳觉醒了金手指扮演系统，扮演神级人物小哥张麒麟。 从此，她过沙漠，下冰川，斩异兽，破机关，无所不会，无所不能，假千金等人后悔莫迭，纷纷哭着跪求她救救他们，否则他们无法在国运世界存活。 墨琦琳微微一笑，一脚踢开他们，滚，她就不救，怎么着？",
        "cover": "https://p3-reading-sign.fqnovelpic.com/novel-pic/p2o11c6828c5c1300548da25b43a29600de~tplv-resize:225:0.image?lk3s=5b7047ff&x-expires=1781853740&x-signature=KwdPaHyujJ4p5qOhqojMdcPDJYQ%3D",
        "url": "https://fanqienovel.com/page/7365424975622179902"
      },
      {
        "title": "无限游戏：别急，骗完你的骗你的",
        "author": "来发财",
        "reads": "7.2万",
        "intro": "【无CP+爽文+游戏+前期独狼】 　　[欢迎来到无限欢乐游戏，失败三次，您将死亡] 　　当其他玩家靠着各种攻击技能大杀四方时，蓝星新人云岑看着自己的本源技陷入沉思—— 　　【啊？你能听见我说话？】 　　这破技能除了能听马桶抱怨便秘、听路灯倾诉孤独，还能干嘛？！ 　　算了，技能不够，骗术来凑。 　　从此游戏多了个ID【弱小可怜又无助】的玩家。 　　—— 　　这是一个汇聚十几个星系的生存游戏，集齐卡牌，才能兑换通往新世界的通行证。 　　作为初入游戏的蓝星人，云岑本是所有玩家眼中最弱的存在。 　　直到其他星系联合发布了一条天价悬赏： 　　【全服通缉蓝星玩家“弱小可怜又无助”！】 　　【若有人能将其击杀，联盟将联合奖励：超星道具卡×5！】 　　—— 　　日常小游戏，但打破常规玩法 　　目前写到的游戏有：真心话大冒险、一二三木头人、丢手绢、狼人杀、捉迷藏、石头剪刀布、欢乐斗地主、扫雷、剧本杀、飞行棋、开心消消乐、开心牧场、谁是卧底、海龟汤 PS：有直播设定，但不会细写，没有弹幕，不喜欢有直播因素的读者慎入",
        "cover": "https://p3-reading-sign.fqnovelpic.com/novel-pic/a97556ef483dcf7c0b47975bb547545f~tplv-resize:225:0.image?lk3s=5b7047ff&x-expires=1781853740&x-signature=l2Ur0sMtPtnKgH7ND7TiOopYc5I%3D",
        "url": "https://fanqienovel.com/page/7572596438383725593"
      },
      {
        "title": "震惊！男友竟是恐怖副本BOSS",
        "author": "拓跋饺子",
        "reads": "7.1万",
        "intro": "【诡异+双强+恐怖副本+轻松搞笑+男友是BOSS+老婆奴+双洁】 男友在自己生日的那天，说因为恐怖副本玩家激增，他作为副本大BOSS需要加班，回不来。 沈嘉禾气笑了，他分明可以说自己出轨了！结果找了个这么荒谬的理由！当天和这死渣男分手，结果当晚就被拽进了恐怖副本中……… ①海岛监狱 沈嘉禾被拉进A级副本中，原本是个大逃杀的游戏，结果看着典狱长精瘦的背影，总觉得有些眼熟，好像在哪里见过似的。 所以她趁乱摸进典狱长的房间，试探性的喊了一声：“林远舟？” 弑杀残忍的典狱长‘噗通’一声跪在了地上，试图狡辩，“老婆，我不是林远舟！” 沈嘉禾：“……” 原来自家男友没有骗她，他真的是恐怖副本BOSS。 ②玩偶庄园 这是一个硕大的玩偶庄园，每当夜幕降临，庄园里的玩偶就会变成诡异。 玩家一旦被诡异找到，也会成为玩偶，永远的留在这个玩偶庄园。 击杀诡异的唯一办法，就是找到和它一样的共生娃娃毁掉！ 沈嘉禾进入副本的当晚，林远舟就将缩小版的狼人娃娃偷偷塞给了她。 沈嘉禾奇怪的在娃娃身上捏了捏，就见眼前的男人红透了脸。 原来这娃娃不仅共生，还共感！ ③森林兽世 ④暗影古堡 ⑤绝命医院 ⑥末日藤蔓 ⑦双生病娇",
        "cover": "https://p3-reading-sign.fqnovelpic.com/novel-pic/p2o01d4cd7371e040b7fa1c81f0011ce1b3~tplv-resize:225:0.image?lk3s=5b7047ff&x-expires=1781853740&x-signature=BJQi%2BJXiQHmcxtSs8Dy2VpN0A2M%3D",
        "url": "https://fanqienovel.com/page/7429187832708598846"
      },
      {
        "title": "盗墓：神豪系统？那我可犯贱了",
        "author": "望启明",
        "reads": "7.1万",
        "intro": "【癫文+ooc+all+女主犯贱】评分刚出，会涨 周妙妙绑定了一个超级辅助神豪系统。 据系统说，只要她把钱花在嫩牛五方的身上，花出去的钱就可以双倍返还成为她的。 系统本以为吴邪这一次有宿主的帮忙，绝对稳了。 没想到周妙妙不走寻常路，钱确实花在了他们五个身上。 但它没想到的是，她居然花钱雇佣黑瞎子打吴邪... 再给吴邪揍了一顿又一顿后，周妙妙赔偿了一笔又一笔的医药费，并且得到了双倍的金钱和快乐。 于是，周妙妙灵机一动，又雇黑瞎子，打王胖子，打解雨臣，打张起灵... 随后，反手雇他们几个，暴揍黑瞎子... 甭管能不能打的过... 医药费和佣金是必须给的... 于是，场面一时间难以控制了起来。 最后，周妙妙得到了金钱和快乐，和他们几个人的围追堵截。 系统：【妙啊！】 周妙妙：【怎么了我的统？】 系统：【我没喊你…你别跟我说话…让我冷静一下…】",
        "cover": "https://p3-reading-sign.fqnovelpic.com/novel-pic/26df070b7a3ffa7eba81a9c3c1b87603~tplv-resize:225:0.image?lk3s=5b7047ff&x-expires=1781853740&x-signature=Kzvl3GaTAP3CDFG%2BeLuHQp0enS4%3D",
        "url": "https://fanqienovel.com/page/7604100445681765438"
      },
      {
        "title": "网恋到恐怖boss，逃跑被亲哭",
        "author": "疯狂的嘎朵拉",
        "reads": "6.9万",
        "intro": "【无限流+甜宠+成长女主+痴汉病娇男主+双洁】 云芙网恋了个男朋友。 联系方式是从梦里梦见的。 男友对她千娇百宠，日日撩夜夜哄，是个妥妥的恋爱脑老婆奴，然而在云芙开学之际想约对方奔现时，男友却支支吾吾不肯见她。 “不见面就分手！” 云芙气呼呼的威胁，下一秒，她坐的校车发生意外失控撞向护栏，就在云芙以为自己会死的时候，凭空一只大手揽住了她的细腰。 低哑危险的嗓音在耳边呢喃：“宝宝，我来找你了。” 再一睁眼，云芙进入了恐怖游戏。 【蔷薇城堡】充满怪异的城堡，夜夜有鬼拿刀砍人，小心行事的云芙只想平安活下去，可恐怖boss看她的眼神愈发湿热黏腻。 【校园诡事】目睹玩家被同桌吃掉了一只手臂后，云芙胆战心惊的默默和自己同桌保持距离，但同桌偷偷在桌底下舔她手怎么办？ 课上，某同桌举手：“老师，我要求云同学当班长。” 云芙：？ 于是，被迫成为班长的云芙被某人天天霸占要求她给他补课，实则是把她堵在无人的教室为所欲为。 某同桌：“班长，你会接吻吗，教我接吻吧。” 【红嫁衣】 【末世沦陷】 【诡秘山村】 【夺命小区】 …… 成功从副本逃离，云芙猛然发现，她送给男友的项链竟然戴在恐怖boss的身上！ 所以，她的男友从来就不是人…… 老婆香香，贴贴~",
        "cover": "https://p3-reading-sign.fqnovelpic.com/novel-pic/p2o7f0d63e62ee254e550fc74c2dec5bce7~tplv-resize:225:0.image?lk3s=5b7047ff&x-expires=1781853740&x-signature=ojr0bMm4Zcim5ExTmx9gfSzFsLs%3D",
        "url": "https://fanqienovel.com/page/7415436476072086590"
      },
      {
        "title": "【杀人游戏】我想活下去",
        "author": "雨戈",
        "reads": "6.7万",
        "intro": "【无限流】+【无cp】+【纯恶女】顶级智斗，夺命游戏；尔虞我诈只为活命。 女主她万般作恶；摒弃良知；一切只为利益。 因为她知道，唯有人吃人，才能变强，才能一步步登上那权利的顶峰。 看她如何从底层蝼蚁，杀出重围，伫立在世界之巅。 看她在棋盘中，屡屡打出亮眼操作，每次逆风翻盘的方法，都绝对出人意料。 游戏只有一人能活？｜那你去死吧 想杀我？｜给你机会也不中用啊 我是蝼蚁？｜嗯，尽说些不爱听的，下辈子注意点。 一切作恶，都只为了活下去！ （ps：拒绝无脑爽，有脑才更爽，越到后期越强，越到后期越爽！！）",
        "cover": "https://p3-reading-sign.fqnovelpic.com/novel-pic/p2oa294855f69bb2a83e5695be08fab8ebf~tplv-resize:225:0.image?lk3s=5b7047ff&x-expires=1781853740&x-signature=OVS%2B4dzOalD%2F8b6c4PVcLxZ0jHE%3D",
        "url": "https://fanqienovel.com/page/7476721263583448088"
      },
      {
        "title": "无限剧本杀：DM掌心病美人",
        "author": "凛冬知更鸟",
        "reads": "5.9万",
        "intro": "【清冷聪慧猫系病美人×凶残腹黑蛇系DM】 【bg+微恐+无限流+剧本杀+微万人迷+1v1甜文】 冷脸萌妹vs笑脸疯批 “你叫××，昨晚，你亲眼目睹了一场杀人案” “作为嫌疑人，请找出真凶，存活到游戏结束” “注意观察罐头里的臼齿，石头里的死胎，枯井下的焚灰……” “总之，亲爱的侦探小姐，祝你好运” 宿眠，一个极其厌世，体弱多病的女大学生，穿进了无限流世界里。 系统让她扮演痴呆小孩，病娇医生，恶魔修女……还不能违背人设，因为一旦人设崩塌，副本DM就会给予恐怖的惩罚。 可为什么每场游戏她遇到的都是同一个DM，而且惩罚和其他玩家还不太一样？？？ 副本一:《孤儿怨》(已完结) 痴呆小孩×疯批院长 副本二:《第二颗心脏》(已完结) 病娇医生×危险患者 副本三:《石胎》(已完结) 恶魔修女×伪善神父 副本四:《毕业诅咒》(已完结) 痴情小尾巴×男鬼校草 …… tips: 1.成长型女主，前期会害怕男主，金手指是自己的智商外加男主战力。 2.双向救赎和互相臣服，女主有心理疾病。 3.SC双洁1v1HE",
        "cover": "https://p3-reading-sign.fqnovelpic.com/novel-pic/fc01ee67c94c80e0179321ef4393302a~tplv-resize:225:0.image?lk3s=5b7047ff&x-expires=1781853740&x-signature=%2BUb3waLsIa794a1JKVzy6uxeP0k%3D",
        "url": "https://fanqienovel.com/page/7579288281993464894"
      },
      {
        "title": "糟糕！惊悚boss又凶又黏人",
        "author": "流浪苍耳",
        "reads": "5.8万",
        "intro": "【无限流＋多副本＋推理＋双洁＋对抗路情侣】 【男主惊悚boss假扮玩家，前期男女主都想弄死对方，主无限流副本故事】 姜恋被拉进惊悚游戏中，别人避之不及的游戏，她却苦心孤诣找寻了三年。 初进副本，为自保说谎，却引起假扮精神病玩家的黑心boss关注。 ①【玫瑰酒店（猛诡酒店）】 黑心boss：你的面具很有趣，揭开后的面孔很丑恶吧！ 姜恋：每个人都有面具，你不也是？（使劲摸一把腹肌）你在精神病院练腹肌？ boss：占我便宜？无所谓，这个副本全员恶人，我要他们都凉凉。 其他现实中有恶行的玩家，都陆续在副本中遭受恶报。 但姜恋出乎意料，苟到了最后。 出副本前，用一把匕首刺中boss。 某boss：那一刀刺在了我的心上，你得负责！ ②【年兽】 被鞭炮声驱赶的，究竟是猛兽，还是随着年回乡、年过了便匆匆离开的打工牛马？ ③【名利场】 ④【玫瑰酒店2】 ⑤【……】 —— boss前期：虽然你很苟，但我能把你坑成死狗！被我坑凉，就是你的命。 boss后期：老婆别凉，求你！我愿倾尽全部，只要你能活下去。 姜恋：什么惊悚boss？……狗都不吃的恋爱脑！",
        "cover": "https://p3-reading-sign.fqnovelpic.com/novel-pic/p2o827817ac79120bc5d59a999c1dc981c3~tplv-resize:225:0.image?lk3s=5b7047ff&x-expires=1781853740&x-signature=JNMVSBqI9VvNc2HmrScakm2iWs4%3D",
        "url": "https://fanqienovel.com/page/7479652263523273753"
      },
      {
        "title": "沙海：喂！你们别变异啊！",
        "author": "不完煦",
        "reads": "5.5万",
        "intro": "【ooc+有自设剧情+无金手指+系统+黑莲花+有变异情况+all】 喻初二十岁，同样失明了二十年，当某一天出现了一个系统，只要获取目标任务的好感度，就可以随着好感度的升高，救治自己的眼睛。 但是当喻初来到这个世界的时候，发现自己的这具身体同样也是眼瞎的。 一睁眼，成了个盲女就算了。 一开口，好感度负五。 喻初觉得这个系统，开局就是在针对她，她什么都没干，就撞了无邪一下，道了歉，还贴心地叫他多喝热水，然后好感度就负了。 而她，一个手无缚鸡之力的瞎子，唯一的武器就是一张贫嘴。 更离谱的是，半夜有什么毛茸茸的东西趴在她胸口，压得她醒不过来。 系统说：能量来源不明，不属于任何已知类别。 喻初：？？？ 这世界到底还有多少惊喜是朕不知道的？ 后来有人握着她的手腕，声音嘶哑：“你是唯一能压制我的人。” 喻初笑了：“所以我是人形镇定剂？” “你非要这么理解也行。” “……滚。” 她想要光明，哪怕要靠近深渊。 可当她终于能看见的时候，第一眼看到的，却并不是他们。",
        "cover": "https://p3-reading-sign.fqnovelpic.com/novel-pic/p2ob61132c0f3563abb4ac979fe6072e3a3~tplv-resize:225:0.image?lk3s=5b7047ff&x-expires=1781853746&x-signature=WnVEG%2FHpc6nw%2FurybLS%2B%2FnIY%2Fw8%3D",
        "url": "https://fanqienovel.com/page/7620798533062380569"
      },
      {
        "title": "全民盗墓：我靠死亡回档秀翻全球",
        "author": "摆烂的馒头",
        "reads": "5.1万",
        "intro": "【新书出分，后期会涨】 【全民盗墓世界+死亡回档+直播+迪化流+无CP大女主】 【排雷：有万人迷情节和男男女女单箭头哦！各项排雷请看第一章开头!】 社畜张开颜猝死后睁开眼，发现自己居然没成盒。 好消息是，她穿越了，坏消息是，穿越的这个平行世界，正在被外星文明按在地上摩擦。 人类文明最后的希望，不是航母核弹，而是——盗墓。 外星人的黑科技降临地球，所有现代武器都成了废铁，唯一能对这些入侵者造成伤害的，是经与外星人同时降临的古墓系统改造后，那些用科学无法解释的玩意儿。 于是，人类的命运，落在一群被系统强制绑定的倒霉蛋身上。 张开颜，光荣入选。 第一次下墓，她眼睁睁看着自己被机关扎成了刺猬。 然后她睁眼，回到了下墓前。 她拥有了死亡回档的能力。 当其他玩家被吓得魂飞魄散时，张开颜开始了她的反向操作。 手滑触发机关？没关系，重来。 队友一不小心凉凉？死一次就救回来了。 遇到无解的千年粽子？她直接抽出一米大刀，来吧宝贝，接受来自姐姐的爱。 别人下墓靠技术，她下墓靠次数。 硬是凭着一条烂命杀出一条血路来，就是最后，她怎么成了全员白月光。",
        "cover": "https://p3-reading-sign.fqnovelpic.com/novel-pic/p2o22cba4b28f97ebdd8ff144e204e204ec~tplv-resize:225:0.image?lk3s=5b7047ff&x-expires=1781853746&x-signature=TATt2UWfG86ME3KdyJ996OaAexY%3D",
        "url": "https://fanqienovel.com/page/7614430898171153433"
      },
      {
        "title": "无限流：摆烂后我封神了",
        "author": "长长长消",
        "reads": "5万",
        "intro": "无cp+系统+迪化流 洛月见一直认为自己是个平凡又普通的人，还有点社恐+面瘫。这样的人扔进人群中毫不起眼，绝对会被所有人忽视掉。 离奇死亡后她被迫进入逃生游戏，她有自知之明，知道自己是绝对没有能力在恐怖逃生游戏中复活的。 就在她纠结到底是要奋力拼一把，还是就此摆烂，突然，她获得了一个完美符合她心意的系统。 摆烂系统：摆烂死亡，直接复活！ 只要宿主在不违规的情况下成功死亡，就可以原地复活，收获1亿现金回到现实世界！ 洛月见邪魅一笑：开摆！ 【恶魔别墅】 洛月见狗狗祟祟的离开房间，欲意作死。 结果，洛月见仿若欧皇附身，随便伸个懒腰，都能避开致命飞箭。 直播间观众震惊：原来是个大佬？！ 洛月见：？ 【死亡沙漠】 洛月见潇洒将自己唯一的水资源倒掉。 下一秒，喝了水的队友B口吐白沫倒地不起。 队友感激涕零：谢大佬提醒！ 洛月见：？ 【长眠地宫】 遍地是毒虫的密道，洛月见直接明演，直接走了进去。 下一秒，毒虫面对洛月见四散奔逃。 队友and观众高呼：不愧是大佬！ 洛月见：？ 面对越来越多的粉丝，以及越来越远的目标。 洛月见笑的狰狞：到底是谁在演我？！",
        "cover": "https://p3-reading-sign.fqnovelpic.com/novel-pic/p2oedac888993929f2c25589afc589c50a4~tplv-resize:225:0.image?lk3s=5b7047ff&x-expires=1781853746&x-signature=ZsdxHtPR%2B5rgHSOp5J9cOjaMOHs%3D",
        "url": "https://fanqienovel.com/page/7197271483859602447"
      },
      {
        "title": "我娇滴滴的，怎么都说我灭诡之神",
        "author": "巢怜云",
        "reads": "4.8万",
        "intro": "【真恐怖游戏+绝对看不见诡异的女主+轻松搞笑】 恐怖游戏降临，人们不仅得面对恐怖的诡异和各种规则，还得面对严重的精神污染，就在人们几乎撑不住时，一个神奇的纸扎铺出现了。 纸扎铺出品，皆是精品。 平安符能瞬间清零所有精神污染。 驱鬼符能瞬杀诡异。 甚至是店里的纸钱，都能驱赶诡异。 … “纸扎铺又上新品了，快抢！” * 马小扁穿越了，穿越到平行时空，从一个贫穷的孤儿，变成一个继承了纸扎铺的贫穷孤儿，身为心理学诈骗预备犯的她，很快发现，这个世界的人相当迷信，嘴里高喊着什么鬼蜮啊，诡异啊，恐怖游戏什么的，就开始拼命砸钱。 迷信好啊，迷信的钱最好赚了！ 她立马开始手动画符纸，诈骗式宣传，高价售卖，一骗一个不吱声。 “小老板，真是太谢谢你了！” 看，他们甚至还要谢谢她。",
        "cover": "https://p3-reading-sign.fqnovelpic.com/novel-pic/p2oe9ac83bf1e508429295167b45d7a983d~tplv-resize:225:0.image?lk3s=5b7047ff&x-expires=1781853746&x-signature=w64M6bkm1jk3cl9S8RrfrMzeh%2Fg%3D",
        "url": "https://fanqienovel.com/page/7501489140878298137"
      },
      {
        "title": "玩家？她是恐怖副本npc哦",
        "author": "岁岁儿",
        "reads": "4.6万",
        "intro": "巫乐是恐怖游戏里面的杀戮npc，在各个副本轮转‘打工’！ 巫乐自由且任性，欺骗玩家，戏耍玩家，恐吓玩家，是她的日常。 　　她时而喜欢假扮玩家，近距离观赏人心险恶，给予玩家希望，最后彻底粉碎，欣赏他们绝望的神情。 　　她时而也会规规矩矩扮演一个合格的恐怖npc，追杀玩家。 　　 　　她喜欢一切漂亮的事物，无聊的时候最爱挑逗自己的那些恐怖npc同事，前提条件是这位npc得够漂亮。 　　反正都是无意识的副本npc,调戏了也不用负责。 　　巫乐想象很美好，直到有一天她发现自己天真了。 　　“巫乐乐，这次为什么不亲我？我这具身体不够漂亮吗？”恐怖boss步步紧逼。 　　········ 　　倒霉的人类被拉入了无限恐怖世界，成为了恐游玩家，他们必须通过一个个副本才能活下去。 　　副本内没有法治可言，充满危机，鬼怪横行，玩家们像蝼蚁一般艰难求生。 　　为了活下去，玩家们学会了踩着同类尸骨，互相欺骗，还有抱老玩家大佬们的大腿！ 　　漂亮诡异的少女，据说是顶级玩家，是公会顶级大佬！ 　　抱到大腿了？ 　　一路惊魂，眼看着离开副本的希望就在眼前，少女化身恶魔:“谁跟你们说我是玩家了？”",
        "cover": "https://p3-reading-sign.fqnovelpic.com/novel-pic/p2oa1b35d36c3b50e2c5cffe409859626ff~tplv-resize:225:0.image?lk3s=5b7047ff&x-expires=1781853746&x-signature=2P300MGYxhojR7fBeFF5JhL%2FjmE%3D",
        "url": "https://fanqienovel.com/page/7389963114571107390"
      },
      {
        "title": "惊悚游戏：我穿越到了童话世界？",
        "author": "火锅涮毛肚",
        "reads": "4.2万",
        "intro": "【暗黑童话+惊悚游戏+直播+爆笑+无cp+非常规结局】 我叫时予，是个精神病人，一觉醒来，被传送进名叫“小红帽”的恐怖游戏。 妈妈的头上正在冒黑气，送给外婆的蛋糕里掺杂了不明种类肉糜…… 游戏情况全球实时直播，人们惊讶的发现： 当其它玩家见到诡异瑟瑟发抖的时候，一个娇小的身影，却早已开始了属于自己的大屠杀…… 游戏一：小红帽 游戏二：灰姑娘 游戏三：拇指姑娘 游戏四：皇帝的新装 游戏五：…… ……",
        "cover": "https://p3-reading-sign.fqnovelpic.com/novel-pic/p2obb90fe216a3e35318fb99c793f5ca9ac~tplv-resize:225:0.image?lk3s=5b7047ff&x-expires=1781853746&x-signature=q7y4c3d7TQkpw1CD9CHkZ5ZuIaw%3D",
        "url": "https://fanqienovel.com/page/7441543479412395032"
      },
      {
        "title": "盗墓：二爷有个反骨崽",
        "author": "鱼aaaaa",
        "reads": "4.1万",
        "intro": "【原创主角+嫩牛五方+All向+主攻+平遗憾】 脑洞大开，新手小白文，主角有点魔丸潜质（大概。。）走剧情 无澈，一个清澈愚蠢的大学生，成了无二白的孩子。 无澈乐疯了，他可以使劲浪了，有人兜底啦，哈哈 无二白也疯了，快让孩子逼疯了。 当初—— 没打算要孩子的无二白突然有了个崽，从此走上了给崽收拾烂摊子的不归路。 而无邪高兴了，因为他终于有兄弟了。以后挨打都有人跟他一起了，高兴的不行。 后来—— “无澈！！”无二白的清静日子一去不复返。 日常深呼吸加河东狮吼。 再后来— 无邪抓狂：“你放下，不准碰！！” 王胖子试图劝架：“咱乖啊，去吃饭，那不能吃！！！熊孩子！！” 黑瞎子崩溃：“那个是真品，很值钱，不能扔！！！” 张麒灵死鱼盯：“不可以！” 谢雨晨掰断了手里的笔：“我让你放下！！” 简介无能，后续还要改。。",
        "cover": "https://p3-reading-sign.fqnovelpic.com/novel-pic/p2o5b38a1f372f84a2cd126e8a7596bf9cb~tplv-resize:225:0.image?lk3s=5b7047ff&x-expires=1781853746&x-signature=%2BLlBDVEL%2BnoG%2BnR7avrp0Wv2NGI%3D",
        "url": "https://fanqienovel.com/page/7613341615322582078"
      },
      {
        "title": "在无限流长的太漂亮是会被亲哭的",
        "author": "美女子牙牙",
        "reads": "3.7万",
        "intro": "［bg+女嬷万人迷+1vn+无限流+女主漂亮娇软可爱+男主阴湿疯批变态坏种+男全洁］ 　 　从小身在有钱家庭却因为身体原因，很少外出的池姝没想到会在自己二十岁生日当天被一个惊悚游戏选中，进入到了无限流世界，成了一名战五渣的新人玩家。 　　没了权势金钱，身娇体软还爱哭的大小姐看着像是连第一关都过不了，但身边突然围上来了一群赶不走的恶犬，一边帮着她过关，一边对着漂亮的大小姐虎视眈眈。 　　直播间的粉丝一开始还在担心这娇气的小美人能活多久，却没想到身娇体软的大小姐靠着一张让神明鬼怪都心软的脸一路过五关斩六将活到了最后。 　　只是副本过着过着，眼看大小姐和身边的恶犬越来越亲密，粉丝笑的越发开心了，当事人却还没意识到事情的严重性，直到有一天池姝被坏男人堵在墙角，亲的不知天地为何物，摁着不让逃走的时候，余光里看见粉丝的一条弹幕，姝姝不知道在无限流长的太漂亮是会被亲哭的吗？ 　　避雷: 　　1.非大女主女强文，万人迷玛丽苏爽文，漂亮娇软怯弱女主，且有时道德感较低，涉及大量女主外貌颜值描写(男性视角大量男凝)存在恶毒女配恶毒男配 详细避雷看第一章૮₍◜ෆ◝.",
        "cover": "https://p3-reading-sign.fqnovelpic.com/novel-pic/2ca73fd4f45b4762b8a18d24cb984e23~tplv-resize:225:0.image?lk3s=5b7047ff&x-expires=1781853746&x-signature=BFz84Lfnf4F2tilQNgPR517H9i4%3D",
        "url": "https://fanqienovel.com/page/7560332930845789209"
      },
      {
        "title": "盗墓：别不拿NPC当回事",
        "author": "泗九七七",
        "reads": "3.7万",
        "intro": "【系统+ooc+搞笑+无CP】（评分刚出会涨） 重生盗墓世界，直接喜提粽子编制！ 花手女傀、全旋血尸、富贵禁婆轮番上线，靠着崩坏拉满的尸系人设，疯狂攒够复活值。 到头来却才发现一切都是假象，榜一大哥吴邪竟成了备选方案。 没关系，只要没活就往死里折腾！ 是向死而生，还是向生赴死？ 我秦安西尸放荡不羁爱自由。",
        "cover": "https://p3-reading-sign.fqnovelpic.com/novel-pic/p2ob4b80af6bb8997f753cc8f035565a7e6~tplv-resize:225:0.image?lk3s=5b7047ff&x-expires=1781853746&x-signature=ptGLdFt5cA4DreaM%2BnABtjQsJ6I%3D",
        "url": "https://fanqienovel.com/page/7619751669747698750"
      },
      {
        "title": "【末世】别睡觉！会死！",
        "author": "步步见喜",
        "reads": "3.7万",
        "intro": "【重生+无限流+女强+无CP+微群像+梦魇入侵】 倒计时随机出现在城市上空，时间清零时，城市居民强制陷入沉睡，被拉入梦魇世界。 黎戈重生后就一个想法，杀光所有诡异种，干死梦魇！ 起初梦魇怪物们以为黎戈只是个好吃的人类罢了，到后来…… 到底谁才是怪物！食物链的顺序是不是错了喂！ 人类世界里，污染侵蚀，长满人嘴的嗜血山茶花、演唱会上诱惑粉丝化蝶献祭的巨星天王，鲜货火锅店现抠人肠来一份？ 黎戈表示，没什么是一锤子解决不了的。 如果解决不了，那就吃掉吧，反正她一直饿得慌。 当梦魇席卷整个世界，不论是人类中的清醒者还是普通人都绝望时，一人带队杀穿梦魇。 人类清醒者论坛曙光APP： ——恭喜【梦魇是个锤子】击杀灭城级诡异种地狱魔章！ ——恭喜【假面】击杀城级诡异种猩红之眼！ “我是黎戈，食梦貘小队队长，曙光ID【梦魇是个锤子】【假面】。” “你也可以称呼我为诡域支配者，或者……” “梦魇之主。”",
        "cover": "https://p3-reading-sign.fqnovelpic.com/novel-pic/p2od86a11765666ebeee2b72ee2aa14442f~tplv-resize:225:0.image?lk3s=5b7047ff&x-expires=1781853746&x-signature=VeMcPRjgw5PKhUIVk1S5J6vZjJ8%3D",
        "url": "https://fanqienovel.com/page/7581888469618658366"
      }
    ]
  },
  "categories": [
    {
      "name": "悬疑脑洞",
      "trend": {
        "new_count": 29,
        "dropped_count": 19,
        "new_books": [
          "你好诡异Boss，我是来打工的",
          "不要在无限流里招惹精神病！",
          "宿舍求生：开局加入诡异管理群",
          "全民躲猫猫：疯批美人她满级天眼",
          "规则怪谈：王子总是对我垂涎欲滴"
        ],
        "dropped_books": [
          {
            "title": "盗墓：你们偷我家小麒麟？",
            "intro": "（评分刚出，会涨，主角万人迷，目前暂定有cp） 吳谓被倒霉系统绑错穿越到了盗墓世界，收集盗墓世界中的非正常能量。 明明选的是根正苗红的张家麒麟血，却阴差阳错被吳家捡回去养了十几年。 本想藏好血脉，跟着"
          },
          {
            "title": "什么变态，那是我老公",
            "intro": "明想嫁给谢均，结婚两年，生活平淡且幸福。 可这一天，她突然看到了出现的弹幕。 【笑死，女配不会以为她会很幸福吧，嫁给了一个变态杀人狂魔】 【都不知道自己怎么死的，还在那沾沾自喜】 明想：胡说，我老公怎"
          },
          {
            "title": "盗墓笔记：原来是故人没死",
            "intro": "［评分刚出，会涨］【张家麒麟女+cp张起灵+战斗力天花板+天授失忆】 苦中作乐花孔雀×失忆寻妻小苦瓜 张家末代族长和族长夫人，为何落得对面人不识？ 为何麒麟女苦苦躲藏数年？ ———————— 狗五爷："
          },
          {
            "title": "盗墓：开局给小花推销乾坤袋",
            "intro": "【all女主】 沈玉汐绑定了一个修真系统，正准备穿到修真界开启爽文人生，然而穿越中途系统能量耗尽，她被丢到了1998年的盗墓世界。 没有钱，还是个黑户，她只好凭借半吊子的修真技能努力抱大腿。 抱着抱着"
          },
          {
            "title": "漂亮小可怜在暗黑童话被疯狂觊觎",
            "intro": "【暗黑童话+万人迷+女嬷向+1vN+男全洁】 【暗黑向，含墙制，球禁等】 【非女强非大女主，妹宝柔弱爱哭还胆小】 ... 下面是简介：诡异游戏降临，人类需要通关才可生存。 而云姝，一个漂亮的不像话的柔"
          }
        ],
        "top_risers": [],
        "top_fallers": [
          {
            "title": "盗笔：我真不是张家人，真的！",
            "change": "-7"
          }
        ],
        "reads_growth": [
          {
            "title": "盗笔：我真不是张家人，真的！",
            "growth": "+8000"
          }
        ],
        "summary": "新增29本上榜；19本掉出（《盗墓：你们偷我家小麒麟？》、《什么变态，那是我老公》、《盗墓笔记：原来是故人没死》、《盗墓：开局给小花推销乾坤袋》、《漂亮小可怜在暗黑童话被疯狂觊觎》）；《盗笔：我真不是张家人，真的！》阅读量+8000。"
      },
      "books": [
        {
          "title": "你好诡异Boss，我是来打工的",
          "author": "七一子",
          "reads": "31.8万",
          "intro": "【实体出版已签约】 【女频无CP无限流+剧情流+微惊悚】 失业第一天，黎雾手机上莫名多了一个APP。 上面的工作简单且高薪，一看就是杀猪盘。 黎雾：“去！去的就是杀猪盘。” 她的工作任务很简单： 【小女孩保姆——5000元/天】 【整形医院护士——10000/天】 【农村守村人——30000/天】 工作内容透明，工资日结，杀猪盘她也认了。 …… 入职保姆第一天，小女孩死了。 黎雾：“建议公司赔偿烧纸钱。” 入职护士俩小时，不小心被人爆了头。 黎雾：“希望保险管管这事。” 成为守村人的夜晚，村子烧起来了。 黎雾：“受工伤的话建议三倍赔偿。” 别人都在工作中抱头鼠窜尖叫哭嚎之际，黎雾早已默默成为了优秀员工，名字牢牢挂在榜一。 她的留言受全员工瞻仰： “人钱九九。”",
          "cover": "https://p3-reading-sign.fqnovelpic.com/novel-pic/75d653a64683d66c61a50d7f3e955814~tplv-resize:225:0.image?lk3s=5b7047ff&x-expires=1781853736&x-signature=AFUFjmL%2FAQWGETCynLE8ZEM4lko%3D",
          "url": "https://fanqienovel.com/page/7542165189974576190"
        },
        {
          "title": "不要在无限流里招惹精神病！",
          "author": "灼云客",
          "reads": "24.6万",
          "intro": "【无限流+爽文+团队热血群像+微解密+惊悚逃生】 【顶级天赋·能文能武·冷幽默大女主，和她各显其能的队友们】 起初那些变态观众们以为，某个穿病号服的可怜女人，在第一局就要惨死夜里。 直到他们亲眼见证，她哼着小曲，游刃有余，以一己之力坑杀全局竞争者，人气引爆了直播间。 “疯子！这就是个不折不扣的疯子啊！” “她好帅，我好爱！” 温柔神性的假面被撕碎，蛰伏的凶兽露出獠牙。 是盗贼，是杀手，天赋超绝的鬼才，无所畏惧的斗士。 这场厄运游戏，终于迎来了新的主宰。 —————— 阅读须知： 1.女主经常装疯卖傻逗别人玩，实际上是绝对强者，团队核心，不存在女强男更强； 2.没有完美性格，也没有绝对道德，尤其是女主，她随心所欲； 3.无固定感情线，团队关系好，所有人都爱女主（任何层面的爱）； 4.团队男女成员均有，核心三位都是女性，男性也各具特色，大家会穿插进入副本； 5.直播间存在各种奇葩观众，会产生低级言论，有吵架对立的情况； 6.本文纯架空背景，私设众多，与现实毫无关联，请勿过度考究，或者自我代入； 7.创作自由，一切为剧情和角色服务，遣词造句我会自行斟酌，拒绝任何形式的写作指导。",
          "cover": "https://p3-reading-sign.fqnovelpic.com/novel-pic/p2oee0b715bbc12c5b4bdff8b34dfc75260~tplv-resize:225:0.image?lk3s=5b7047ff&x-expires=1781853736&x-signature=uKa5L5Utuik%2FPT5tHPdDMi0tMSI%3D",
          "url": "https://fanqienovel.com/page/7592919783155190808"
        },
        {
          "title": "宿舍求生：开局加入诡异管理群",
          "author": "27sui",
          "reads": "17.6万",
          "intro": "【无CP+爽文+塔防+诡异+求生+大佬】 　　江浸月在即将签署家人《手术知情同意书》的下一秒，眼前一黑被拉入宿舍求生游戏。 　　夜晚七点一到，门外开始出现恐怖的诡异，它们在走廊上游荡，时刻准备破门而入。 　　活下去的唯一方法就是升级宿舍大门，升级武器炮台，开门抢夺宝箱。 　　永冻深林、幽灵诡船、规则怪谈、欲望赌场、太平医院…… 　　江浸月手握【管理群】游走在诡异与玩家之间，售卖消息，抢占先机，坑蒙拐骗，只为活着回去。 　　无CP女强爽文，大多数是女角色，欢迎入坑，绝不憋屈！\\( ͯω ͯ)/",
          "cover": "https://p3-reading-sign.fqnovelpic.com/novel-pic/p2odff36b7896a104958353d0a38b2bbf5c~tplv-resize:225:0.image?lk3s=5b7047ff&x-expires=1781853736&x-signature=QXXTrX15EFaNHk%2Bvq3YaC1naxYI%3D",
          "url": "https://fanqienovel.com/page/7623619349001014334"
        },
        {
          "title": "全民躲猫猫：疯批美人她满级天眼",
          "author": "油炸雪梨",
          "reads": "15.7万",
          "intro": "【评分刚开，会涨的】【游戏入侵+躲猫猫+直播+女主+无CP】 核战之后，蓝星已成焦土，躲猫猫是人类唯一的希望。 全球躲猫猫游戏降临，被选中的人将代表国家出战，胜则抽取奖励，败则领土沦陷！ 当龙国第四十四轮参赛者林岁安出现时，弹幕哀嚎： “穿病号服？踩着拖鞋？完了，龙国气运已尽！” 然而，当其他选手躲在柜子里瑟瑟发抖时，林岁安在诡异眼皮子底下吃小蛋糕； 当小鬼子被诡异镰刀腰斩时，林岁安在窗外卡BUG逗诡异玩。 全世界都疯了：“让你去和诡异躲猫猫，你在这儿当自家后花园呢？” 林岁安拎着刚抢来的神秘道具，歪头一笑：“不好意思，精神病院住久了，看谁都像好人。” ----- 【排雷：1.没那么惊悚；2.私设，诡异不是中式诡异，均为改造形态；3.文中有鬼魂，但不是诡异。】",
          "cover": "https://p3-reading-sign.fqnovelpic.com/novel-pic/p2oa938b4c249ce755b0dd05758b3cc9ea2~tplv-resize:225:0.image?lk3s=5b7047ff&x-expires=1781853736&x-signature=ghDa%2BzCW%2Fw8MAAcmqqn2SJIjw5s%3D",
          "url": "https://fanqienovel.com/page/7615645509008493593"
        },
        {
          "title": "规则怪谈：王子总是对我垂涎欲滴",
          "author": "总有青葱",
          "reads": "15.5万",
          "intro": "【已签出版】【短剧漫剧已上线】 【无cp➕无限流➕惊悚游戏➕无国运➕暗黑童话】 妙龄少女在午夜低声哭泣 英俊潇洒的王子在夜晚变成嗜血“野兽” 灰姑娘惨死在舞会当夜 惊悚游戏被裹上玻璃糖纸，伪装成甜蜜的糖果。美好的童话世界背后，究竟隐藏着什么…… —— 怪谈降临地球，全球人口在一个月内骤减20亿。 　　图南被怪谈选中，抽签怪谈分类的时候，她赌上了自己全部的运气。 　　“叮咚！恭喜您抽中童话分类，您的运气真是无与伦比。作为整个怪谈世界最梦幻最安全的怪谈，童话世界绝对是您居家旅行出行必备的不二之选！” 　　请牢记童话世界的绝对守则： 　　作为童话人物，请牢记你的人设！ 　 　　最后，欢迎您来到童话世界！ 　　美人鱼、灰姑娘、豌豆公主…… 等等……这个长着一张嘴的童话书又是什么东西？ 会有惊悚诡异的元素，胆子特别小的慎入～ 内含多种元素，不单纯为规则怪谈，部分副本规则存在感极弱",
          "cover": "https://p3-reading-sign.fqnovelpic.com/novel-pic/5c74a50bc0362f2b0bd339c18e09223e~tplv-resize:225:0.image?lk3s=5b7047ff&x-expires=1781853736&x-signature=o5unF3rFWxieR0qQ%2FT9OtSJoqPU%3D",
          "url": "https://fanqienovel.com/page/7400699192022158361"
        },
        {
          "title": "我还能在规则怪谈里塌房不成？",
          "author": "喜杳",
          "reads": "15万",
          "intro": "【无限流+规则怪谈+惊悚游戏+女强团队+集体脑子不正常】 出道前夕，时厘所在的组合惨遭队友背刺，背上了霸凌黑锅。 出道失败，队友美美赢得了网友的怜爱，重新出道风生水起，时厘的社交帐号至今还被对方的脑残粉们团建追骂。 好巧不巧，被公司雪藏的第三年，惊悚降临。 【坐标：蓝星，惊悚国运战场已过审。】 【正在随机抽取本次惊悚乐园的主题——】 【叮！本次主题为……KPOP爱豆团体！】 …… 【爱豆生存指南】 （蛋糕的烛火熄灭，你将只剩下登顶这一条生路，为了你的生命安全，请务必遵守以下规则：） 【一、爱豆为贩卖幻想的职业，任何恋爱行为将视为偶像失格。】 【二、宿舍并非绝对安全，若发现私生潜入的痕迹，请及时反锁房间的门窗……但万一，它就藏身在你的房间里面呢？】 【三、时刻遵守爱豆的职业素养，请拒绝以下行为：签售会切小屏，私联粉丝，舞台划水……】 【四、在粉丝面前时刻保持团魂，没有团魂的组合是一盘散沙，哪怕装……也要装得体面。】",
          "cover": "https://p3-reading-sign.fqnovelpic.com/novel-pic/p2oef36e9704ab627a868e2c04199450612~tplv-resize:225:0.image?lk3s=5b7047ff&x-expires=1781853736&x-signature=sM81m7bid60BxrhOSeFlqMdlmHI%3D",
          "url": "https://fanqienovel.com/page/7358402657045711896"
        },
        {
          "title": "惊悚游戏：从萝莉开始无限逃生",
          "author": "咸鱼五二",
          "reads": "12.3万",
          "intro": "【无限流+无cp+惊悚游戏+成长型女主+微群像】 一张特殊的卡片，引领身处绝境的人，进入无限惊悚游戏…… 活下去，就有机会获得数之不尽的财富，成为人上人。 活不下去，就会成为各种怨灵的养料，在离开游戏后莫名其妙死亡。 你，做好进入游戏的准备了吗？ —— 没有准备好也没有关系，你没有选择的余地。 欢迎进入惊悚游戏，花槐。",
          "cover": "https://p3-reading-sign.fqnovelpic.com/novel-pic/p2oe8ada7be06970049d33cbe39fc60549a~tplv-resize:225:0.image?lk3s=5b7047ff&x-expires=1781853736&x-signature=7Fvz2AF0bpN%2FKY6CMJTNqJVopLw%3D",
          "url": "https://fanqienovel.com/page/7441088503900818494"
        },
        {
          "title": "在恐怖游戏里谈的恋爱千奇百怪",
          "author": "奔跑的桃子",
          "reads": "11.3万",
          "intro": "白瑶成了诸多恐怖世界里空有美貌，且满身铜臭味的恶毒女配。 系统给她抛下“攻略”两个字后就因为信号不好失联了。 她看过那么多小说，很懂套路，不就是要她去攻略有悲惨遭遇的男人吗？ 她在看到某人的第一眼时，能察觉对方身上出现的暗红色光芒，她猜那一定就是自己的攻略对象，于是—— 在闹鬼的寄宿制校园里，她捡到了被人欺负的单纯少年，她给他补课，给他送花，与他躲在死过人的美术室里偷偷的搂搂抱抱。 在六人逃生的废弃医院，她救下了被所有人视为累赘而丢下的病弱少年，她给他送资源，给他送装备，与他藏在衣柜里小心的亲吻。 在危机遍布的海岛，看到那坨黑色带着触手的形似章鱼的生物，她也来者不拒，把黑色怪物藏在了自己的口袋里，它一天天长大，最后有了人的形状，她觉得可以教它亲吻了。 系统重新上线，失声惊叫，“你究竟是怎么能做到和那么多鬼怪BOSS谈恋爱的啊！” 白瑶:“你不是说让我攻略他们？” 系统崩溃，“我是让你把游戏攻略成功活到最后，没有叫你嫖BOSS 啊！” 白瑶:“啊这……” 不可言说的怪物身体撕成两半，它的触手把藏起来的贝壳都送到了她的面前，“瑶瑶，亲我呀。” 白瑶:好感度都刷满了，不亲说的过去？",
          "cover": "https://p3-reading-sign.fqnovelpic.com/novel-pic/p2o2c27e0bb82d6b5ba94bfb4942e8d542c~tplv-resize:225:0.image?lk3s=5b7047ff&x-expires=1781853736&x-signature=5OHu3bRfSEtHOTEemF8SwAkt%2Fr0%3D",
          "url": "https://fanqienovel.com/page/7250087472565062656"
        },
        {
          "title": "国运怪谈，我让纯情男鬼多子多福",
          "author": "卿城之墨",
          "reads": "10.3万",
          "intro": "【评分刚出，后面会涨的】【规则怪谈+多子多福+男全洁+国运+爽文+直播+生存】 “放肆！不知廉耻！” 沈修竹被按在棺材里时，红透了耳根，声音颤抖得像个受惊的雏儿。 他是杀人不眨眼的S级厉鬼，却被林软心一个“平地摔”抱大腿喊相公搞得CPU烧毁。 林软心：哎呀，系统说你欲望值100，你装什么清高呢？（挑眉） 这就是林软心的日常：在规则怪谈里撩最凶的鬼，生最强的娃。 别国选手：救命！鬼医生拿手术刀过来了！ 林软心：白医生，我心口疼，你摸摸看是不是缺个女朋友？（无辜眨眼） 结果：白医生手抖了，心动了，龙国寿命涨了，雪花画面又亮了。 她不仅是在逃生，她是在治愈这些病娇、阴湿、傲娇的男鬼们。 “软心，只要你别看别人，命都给你。” 面对28个顶级男神的病娇占有欲，林软心表示：我只是想救国，不是想腰折啊！",
          "cover": "https://p3-reading-sign.fqnovelpic.com/novel-pic/p2o06642b11742f9d1d5e838aa7beb1c792~tplv-resize:225:0.image?lk3s=5b7047ff&x-expires=1781853736&x-signature=J0bEdGabsiGB5glgK2lufVKeqCQ%3D",
          "url": "https://fanqienovel.com/page/7613722976994724889"
        },
        {
          "title": "状元她在恐怖游戏杀疯了",
          "author": "吃饭第一名咋了",
          "reads": "9.5万",
          "intro": "评分刚开，后面会涨 【无限流+惊悚游戏+烧脑悬疑+无cp】 季遥，理科省状元，重度游戏宅，带着她那随时会宕机的身体穿进惊悚游戏。 全网直播间都在等这个粉色头发的“脆皮花瓶”暴毙，赌她活不过三秒。 直到—— 规则杀人，她冷笑一声，讽刺副本逻辑漏洞比女娲补天的窟窿还大。 怪物索命，她头也不回，直接被猫主子驮着提前三秒站在生路尽头。 终焉降临，她双眼赤红，嘶吼既然万物并非偶然那我便能算出一切。 观众从鄙夷、崩溃，到彻底被圈粉。 别人在挣扎尖叫，季遥在刷分通关。 在这场名为「寒武纪」的残酷进化中， 她是唯一的生存变量，也是游戏的终结真神。 ——·——·—— 阅读须知： 1.暗黑叙事·人性剖析·部分情节掉San预警 2.没有重生/系统，脑子就是最强外挂！",
          "cover": "https://p3-reading-sign.fqnovelpic.com/novel-pic/p2o2f48d6698cc111520e3b9ba3e030da7f~tplv-resize:225:0.image?lk3s=5b7047ff&x-expires=1781853736&x-signature=8fxVPQz7i5Jf2PhuAxRzfBAj69M%3D",
          "url": "https://fanqienovel.com/page/7533610495371136024"
        },
        {
          "title": "盗笔：我真不是张家人，真的！",
          "author": "想要发财的富贵",
          "reads": "9.5万",
          "intro": "【刚出分，后续会涨。无cp，人物私设原著土著。有回忆杀很多，非爽文。不是吴邪黑！不黑主角团！简介无力。有点火葬场和日常文的特色】 张安没有想到只是一个姓，会给他的人生带来天翻地覆的变化。 他和一个叫关根的初遇，因为他藏着右手，他就问他是不是张家人。 张安摇头，他不知道什么是张家人，藏着右手当然是有他的原因。 后来，他遇到了很多人，他们都把他当成了张家人，无论张安怎么解释，他们都不相信。 张安没招了，一个装睡的人是永远叫不醒的，更何况是这么多装睡的人。 于是他成了吴邪计划里的第一个棋子，也是后来计划里十七个少年中唯一“死”掉的那个。 张安在长白山崖迎来了新生，只是没想到一场意外让他们重逢。 他们都以为人死了，没想到在雨村他们又相遇了。 …… 吴邪看着“沈姑姑”作画的背影，想起门后那幅旧画。 王胖子隔着墨镜，再也看不见“沈祖祖”眼里曾如月牙弯起的笑意。 黑瞎子看着他戴的墨镜，一度怀疑这是影分身。 张起灵沉默注视，他认得那双眼睛，却不懂族人为何否认自己的身份。 黎簇拽住他的衣袖，声音发颤：“小安哥，我没家了，你也不要我了吗？” 张安坐在悬崖边，心想他要回家了，这些人又唱又跳的干什么。",
          "cover": "https://p3-reading-sign.fqnovelpic.com/novel-pic/p2o0ce462149e7cd6a8d5239e57ac02f8d2~tplv-resize:225:0.image?lk3s=5b7047ff&x-expires=1781853740&x-signature=38r5LF7sOqWfSoTH4Ck5ENkGhYI%3D",
          "url": "https://fanqienovel.com/page/7618255935110138905"
        },
        {
          "title": "盗笔：大佬？不，是死的太多",
          "author": "映河山",
          "reads": "8.2万",
          "intro": "已恢复更新 虚拟古墓，盗笔同人，无cp，美强惨，主角一个人扮演了整个家族 主角性别为男 谢淮安一朝穿进盗墓笔记，唯一的金手指就是一个随身古墓。 你以为这个古墓很厉害？ 不，它只能模拟各种古墓现场，并让你体验花样死法。 下斗高手？Nonono，他只是在模拟空间里死的太多。 看起来模样不大的清冷少年身上散发着淡淡死气？你死那么多次也可以。 设定：随身古墓可以现场模拟机关，主角不是牛逼，是同一个机关死了太多次，随身古墓内随时读档重来，空间内与正常时间流速不同。 排雷： 双男主标签我以为是俩主角都是男的，不知道要有爱情才能打，但签约后不能更改标签了，所以再次声明非爱情向，原著没有的cp这里不包分配哈。 前期小谢因为穷，没有开痛感屏蔽，这个接受不了的宝宝避一下雷哈。",
          "cover": "https://p3-reading-sign.fqnovelpic.com/novel-pic/p2o85449042a2087e0e91a6aafb0e78830d~tplv-resize:225:0.image?lk3s=5b7047ff&x-expires=1781853740&x-signature=ajGNTQDvFAw%2FF3rqRnDvR13DNyk%3D",
          "url": "https://fanqienovel.com/page/7466117635466333209"
        },
        {
          "title": "国运：扮演张麒麟，我是女版小哥",
          "author": "离殊公子",
          "reads": "7.9万",
          "intro": "女频！女频！女频！ 【爽文+真假千金+原创剧情+直播+绝不原谅+全家火葬场＋无cp】 墨琦琳（音同墨麒麟）穿越到另一个世界的自己身上，另一个世界的自己，是被保姆掉包的豪门真千金，爸爸不疼，妈妈不爱，哥哥弟弟更是极尽嘲讽苛待，只把假千金宠上了天！ 假千金还是朵黑心莲，会演戏，会算计，不但让另一个世界的自己成为全家黑，甚至还成为全豪门黑，全国黑！ 最后，另一个世界的自己在新郎抱着假千金，从婚礼现场离开后，绝望的跳楼而死。 墨琦琳穿越过来，发誓一定要为另一个世界的自己报仇。 只是正当她思索如何报仇的时候，国运降临，她和假千金，以及视她为耻辱的父母、哥哥弟弟们都被国运选中。 国运世界危险重重，一不留神就会丢了性命，幸运的是，墨琦琳觉醒了金手指扮演系统，扮演神级人物小哥张麒麟。 从此，她过沙漠，下冰川，斩异兽，破机关，无所不会，无所不能，假千金等人后悔莫迭，纷纷哭着跪求她救救他们，否则他们无法在国运世界存活。 墨琦琳微微一笑，一脚踢开他们，滚，她就不救，怎么着？",
          "cover": "https://p3-reading-sign.fqnovelpic.com/novel-pic/p2o11c6828c5c1300548da25b43a29600de~tplv-resize:225:0.image?lk3s=5b7047ff&x-expires=1781853740&x-signature=KwdPaHyujJ4p5qOhqojMdcPDJYQ%3D",
          "url": "https://fanqienovel.com/page/7365424975622179902"
        },
        {
          "title": "无限游戏：别急，骗完你的骗你的",
          "author": "来发财",
          "reads": "7.2万",
          "intro": "【无CP+爽文+游戏+前期独狼】 　　[欢迎来到无限欢乐游戏，失败三次，您将死亡] 　　当其他玩家靠着各种攻击技能大杀四方时，蓝星新人云岑看着自己的本源技陷入沉思—— 　　【啊？你能听见我说话？】 　　这破技能除了能听马桶抱怨便秘、听路灯倾诉孤独，还能干嘛？！ 　　算了，技能不够，骗术来凑。 　　从此游戏多了个ID【弱小可怜又无助】的玩家。 　　—— 　　这是一个汇聚十几个星系的生存游戏，集齐卡牌，才能兑换通往新世界的通行证。 　　作为初入游戏的蓝星人，云岑本是所有玩家眼中最弱的存在。 　　直到其他星系联合发布了一条天价悬赏： 　　【全服通缉蓝星玩家“弱小可怜又无助”！】 　　【若有人能将其击杀，联盟将联合奖励：超星道具卡×5！】 　　—— 　　日常小游戏，但打破常规玩法 　　目前写到的游戏有：真心话大冒险、一二三木头人、丢手绢、狼人杀、捉迷藏、石头剪刀布、欢乐斗地主、扫雷、剧本杀、飞行棋、开心消消乐、开心牧场、谁是卧底、海龟汤 PS：有直播设定，但不会细写，没有弹幕，不喜欢有直播因素的读者慎入",
          "cover": "https://p3-reading-sign.fqnovelpic.com/novel-pic/a97556ef483dcf7c0b47975bb547545f~tplv-resize:225:0.image?lk3s=5b7047ff&x-expires=1781853740&x-signature=l2Ur0sMtPtnKgH7ND7TiOopYc5I%3D",
          "url": "https://fanqienovel.com/page/7572596438383725593"
        },
        {
          "title": "震惊！男友竟是恐怖副本BOSS",
          "author": "拓跋饺子",
          "reads": "7.1万",
          "intro": "【诡异+双强+恐怖副本+轻松搞笑+男友是BOSS+老婆奴+双洁】 男友在自己生日的那天，说因为恐怖副本玩家激增，他作为副本大BOSS需要加班，回不来。 沈嘉禾气笑了，他分明可以说自己出轨了！结果找了个这么荒谬的理由！当天和这死渣男分手，结果当晚就被拽进了恐怖副本中……… ①海岛监狱 沈嘉禾被拉进A级副本中，原本是个大逃杀的游戏，结果看着典狱长精瘦的背影，总觉得有些眼熟，好像在哪里见过似的。 所以她趁乱摸进典狱长的房间，试探性的喊了一声：“林远舟？” 弑杀残忍的典狱长‘噗通’一声跪在了地上，试图狡辩，“老婆，我不是林远舟！” 沈嘉禾：“……” 原来自家男友没有骗她，他真的是恐怖副本BOSS。 ②玩偶庄园 这是一个硕大的玩偶庄园，每当夜幕降临，庄园里的玩偶就会变成诡异。 玩家一旦被诡异找到，也会成为玩偶，永远的留在这个玩偶庄园。 击杀诡异的唯一办法，就是找到和它一样的共生娃娃毁掉！ 沈嘉禾进入副本的当晚，林远舟就将缩小版的狼人娃娃偷偷塞给了她。 沈嘉禾奇怪的在娃娃身上捏了捏，就见眼前的男人红透了脸。 原来这娃娃不仅共生，还共感！ ③森林兽世 ④暗影古堡 ⑤绝命医院 ⑥末日藤蔓 ⑦双生病娇",
          "cover": "https://p3-reading-sign.fqnovelpic.com/novel-pic/p2o01d4cd7371e040b7fa1c81f0011ce1b3~tplv-resize:225:0.image?lk3s=5b7047ff&x-expires=1781853740&x-signature=BJQi%2BJXiQHmcxtSs8Dy2VpN0A2M%3D",
          "url": "https://fanqienovel.com/page/7429187832708598846"
        },
        {
          "title": "盗墓：神豪系统？那我可犯贱了",
          "author": "望启明",
          "reads": "7.1万",
          "intro": "【癫文+ooc+all+女主犯贱】评分刚出，会涨 周妙妙绑定了一个超级辅助神豪系统。 据系统说，只要她把钱花在嫩牛五方的身上，花出去的钱就可以双倍返还成为她的。 系统本以为吴邪这一次有宿主的帮忙，绝对稳了。 没想到周妙妙不走寻常路，钱确实花在了他们五个身上。 但它没想到的是，她居然花钱雇佣黑瞎子打吴邪... 再给吴邪揍了一顿又一顿后，周妙妙赔偿了一笔又一笔的医药费，并且得到了双倍的金钱和快乐。 于是，周妙妙灵机一动，又雇黑瞎子，打王胖子，打解雨臣，打张起灵... 随后，反手雇他们几个，暴揍黑瞎子... 甭管能不能打的过... 医药费和佣金是必须给的... 于是，场面一时间难以控制了起来。 最后，周妙妙得到了金钱和快乐，和他们几个人的围追堵截。 系统：【妙啊！】 周妙妙：【怎么了我的统？】 系统：【我没喊你…你别跟我说话…让我冷静一下…】",
          "cover": "https://p3-reading-sign.fqnovelpic.com/novel-pic/26df070b7a3ffa7eba81a9c3c1b87603~tplv-resize:225:0.image?lk3s=5b7047ff&x-expires=1781853740&x-signature=Kzvl3GaTAP3CDFG%2BeLuHQp0enS4%3D",
          "url": "https://fanqienovel.com/page/7604100445681765438"
        },
        {
          "title": "网恋到恐怖boss，逃跑被亲哭",
          "author": "疯狂的嘎朵拉",
          "reads": "6.9万",
          "intro": "【无限流+甜宠+成长女主+痴汉病娇男主+双洁】 云芙网恋了个男朋友。 联系方式是从梦里梦见的。 男友对她千娇百宠，日日撩夜夜哄，是个妥妥的恋爱脑老婆奴，然而在云芙开学之际想约对方奔现时，男友却支支吾吾不肯见她。 “不见面就分手！” 云芙气呼呼的威胁，下一秒，她坐的校车发生意外失控撞向护栏，就在云芙以为自己会死的时候，凭空一只大手揽住了她的细腰。 低哑危险的嗓音在耳边呢喃：“宝宝，我来找你了。” 再一睁眼，云芙进入了恐怖游戏。 【蔷薇城堡】充满怪异的城堡，夜夜有鬼拿刀砍人，小心行事的云芙只想平安活下去，可恐怖boss看她的眼神愈发湿热黏腻。 【校园诡事】目睹玩家被同桌吃掉了一只手臂后，云芙胆战心惊的默默和自己同桌保持距离，但同桌偷偷在桌底下舔她手怎么办？ 课上，某同桌举手：“老师，我要求云同学当班长。” 云芙：？ 于是，被迫成为班长的云芙被某人天天霸占要求她给他补课，实则是把她堵在无人的教室为所欲为。 某同桌：“班长，你会接吻吗，教我接吻吧。” 【红嫁衣】 【末世沦陷】 【诡秘山村】 【夺命小区】 …… 成功从副本逃离，云芙猛然发现，她送给男友的项链竟然戴在恐怖boss的身上！ 所以，她的男友从来就不是人…… 老婆香香，贴贴~",
          "cover": "https://p3-reading-sign.fqnovelpic.com/novel-pic/p2o7f0d63e62ee254e550fc74c2dec5bce7~tplv-resize:225:0.image?lk3s=5b7047ff&x-expires=1781853740&x-signature=ojr0bMm4Zcim5ExTmx9gfSzFsLs%3D",
          "url": "https://fanqienovel.com/page/7415436476072086590"
        },
        {
          "title": "【杀人游戏】我想活下去",
          "author": "雨戈",
          "reads": "6.7万",
          "intro": "【无限流】+【无cp】+【纯恶女】顶级智斗，夺命游戏；尔虞我诈只为活命。 女主她万般作恶；摒弃良知；一切只为利益。 因为她知道，唯有人吃人，才能变强，才能一步步登上那权利的顶峰。 看她如何从底层蝼蚁，杀出重围，伫立在世界之巅。 看她在棋盘中，屡屡打出亮眼操作，每次逆风翻盘的方法，都绝对出人意料。 游戏只有一人能活？｜那你去死吧 想杀我？｜给你机会也不中用啊 我是蝼蚁？｜嗯，尽说些不爱听的，下辈子注意点。 一切作恶，都只为了活下去！ （ps：拒绝无脑爽，有脑才更爽，越到后期越强，越到后期越爽！！）",
          "cover": "https://p3-reading-sign.fqnovelpic.com/novel-pic/p2oa294855f69bb2a83e5695be08fab8ebf~tplv-resize:225:0.image?lk3s=5b7047ff&x-expires=1781853740&x-signature=OVS%2B4dzOalD%2F8b6c4PVcLxZ0jHE%3D",
          "url": "https://fanqienovel.com/page/7476721263583448088"
        },
        {
          "title": "无限剧本杀：DM掌心病美人",
          "author": "凛冬知更鸟",
          "reads": "5.9万",
          "intro": "【清冷聪慧猫系病美人×凶残腹黑蛇系DM】 【bg+微恐+无限流+剧本杀+微万人迷+1v1甜文】 冷脸萌妹vs笑脸疯批 “你叫××，昨晚，你亲眼目睹了一场杀人案” “作为嫌疑人，请找出真凶，存活到游戏结束” “注意观察罐头里的臼齿，石头里的死胎，枯井下的焚灰……” “总之，亲爱的侦探小姐，祝你好运” 宿眠，一个极其厌世，体弱多病的女大学生，穿进了无限流世界里。 系统让她扮演痴呆小孩，病娇医生，恶魔修女……还不能违背人设，因为一旦人设崩塌，副本DM就会给予恐怖的惩罚。 可为什么每场游戏她遇到的都是同一个DM，而且惩罚和其他玩家还不太一样？？？ 副本一:《孤儿怨》(已完结) 痴呆小孩×疯批院长 副本二:《第二颗心脏》(已完结) 病娇医生×危险患者 副本三:《石胎》(已完结) 恶魔修女×伪善神父 副本四:《毕业诅咒》(已完结) 痴情小尾巴×男鬼校草 …… tips: 1.成长型女主，前期会害怕男主，金手指是自己的智商外加男主战力。 2.双向救赎和互相臣服，女主有心理疾病。 3.SC双洁1v1HE",
          "cover": "https://p3-reading-sign.fqnovelpic.com/novel-pic/fc01ee67c94c80e0179321ef4393302a~tplv-resize:225:0.image?lk3s=5b7047ff&x-expires=1781853740&x-signature=%2BUb3waLsIa794a1JKVzy6uxeP0k%3D",
          "url": "https://fanqienovel.com/page/7579288281993464894"
        },
        {
          "title": "糟糕！惊悚boss又凶又黏人",
          "author": "流浪苍耳",
          "reads": "5.8万",
          "intro": "【无限流＋多副本＋推理＋双洁＋对抗路情侣】 【男主惊悚boss假扮玩家，前期男女主都想弄死对方，主无限流副本故事】 姜恋被拉进惊悚游戏中，别人避之不及的游戏，她却苦心孤诣找寻了三年。 初进副本，为自保说谎，却引起假扮精神病玩家的黑心boss关注。 ①【玫瑰酒店（猛诡酒店）】 黑心boss：你的面具很有趣，揭开后的面孔很丑恶吧！ 姜恋：每个人都有面具，你不也是？（使劲摸一把腹肌）你在精神病院练腹肌？ boss：占我便宜？无所谓，这个副本全员恶人，我要他们都凉凉。 其他现实中有恶行的玩家，都陆续在副本中遭受恶报。 但姜恋出乎意料，苟到了最后。 出副本前，用一把匕首刺中boss。 某boss：那一刀刺在了我的心上，你得负责！ ②【年兽】 被鞭炮声驱赶的，究竟是猛兽，还是随着年回乡、年过了便匆匆离开的打工牛马？ ③【名利场】 ④【玫瑰酒店2】 ⑤【……】 —— boss前期：虽然你很苟，但我能把你坑成死狗！被我坑凉，就是你的命。 boss后期：老婆别凉，求你！我愿倾尽全部，只要你能活下去。 姜恋：什么惊悚boss？……狗都不吃的恋爱脑！",
          "cover": "https://p3-reading-sign.fqnovelpic.com/novel-pic/p2o827817ac79120bc5d59a999c1dc981c3~tplv-resize:225:0.image?lk3s=5b7047ff&x-expires=1781853740&x-signature=JNMVSBqI9VvNc2HmrScakm2iWs4%3D",
          "url": "https://fanqienovel.com/page/7479652263523273753"
        },
        {
          "title": "沙海：喂！你们别变异啊！",
          "author": "不完煦",
          "reads": "5.5万",
          "intro": "【ooc+有自设剧情+无金手指+系统+黑莲花+有变异情况+all】 喻初二十岁，同样失明了二十年，当某一天出现了一个系统，只要获取目标任务的好感度，就可以随着好感度的升高，救治自己的眼睛。 但是当喻初来到这个世界的时候，发现自己的这具身体同样也是眼瞎的。 一睁眼，成了个盲女就算了。 一开口，好感度负五。 喻初觉得这个系统，开局就是在针对她，她什么都没干，就撞了无邪一下，道了歉，还贴心地叫他多喝热水，然后好感度就负了。 而她，一个手无缚鸡之力的瞎子，唯一的武器就是一张贫嘴。 更离谱的是，半夜有什么毛茸茸的东西趴在她胸口，压得她醒不过来。 系统说：能量来源不明，不属于任何已知类别。 喻初：？？？ 这世界到底还有多少惊喜是朕不知道的？ 后来有人握着她的手腕，声音嘶哑：“你是唯一能压制我的人。” 喻初笑了：“所以我是人形镇定剂？” “你非要这么理解也行。” “……滚。” 她想要光明，哪怕要靠近深渊。 可当她终于能看见的时候，第一眼看到的，却并不是他们。",
          "cover": "https://p3-reading-sign.fqnovelpic.com/novel-pic/p2ob61132c0f3563abb4ac979fe6072e3a3~tplv-resize:225:0.image?lk3s=5b7047ff&x-expires=1781853746&x-signature=WnVEG%2FHpc6nw%2FurybLS%2B%2FnIY%2Fw8%3D",
          "url": "https://fanqienovel.com/page/7620798533062380569"
        },
        {
          "title": "全民盗墓：我靠死亡回档秀翻全球",
          "author": "摆烂的馒头",
          "reads": "5.1万",
          "intro": "【新书出分，后期会涨】 【全民盗墓世界+死亡回档+直播+迪化流+无CP大女主】 【排雷：有万人迷情节和男男女女单箭头哦！各项排雷请看第一章开头!】 社畜张开颜猝死后睁开眼，发现自己居然没成盒。 好消息是，她穿越了，坏消息是，穿越的这个平行世界，正在被外星文明按在地上摩擦。 人类文明最后的希望，不是航母核弹，而是——盗墓。 外星人的黑科技降临地球，所有现代武器都成了废铁，唯一能对这些入侵者造成伤害的，是经与外星人同时降临的古墓系统改造后，那些用科学无法解释的玩意儿。 于是，人类的命运，落在一群被系统强制绑定的倒霉蛋身上。 张开颜，光荣入选。 第一次下墓，她眼睁睁看着自己被机关扎成了刺猬。 然后她睁眼，回到了下墓前。 她拥有了死亡回档的能力。 当其他玩家被吓得魂飞魄散时，张开颜开始了她的反向操作。 手滑触发机关？没关系，重来。 队友一不小心凉凉？死一次就救回来了。 遇到无解的千年粽子？她直接抽出一米大刀，来吧宝贝，接受来自姐姐的爱。 别人下墓靠技术，她下墓靠次数。 硬是凭着一条烂命杀出一条血路来，就是最后，她怎么成了全员白月光。",
          "cover": "https://p3-reading-sign.fqnovelpic.com/novel-pic/p2o22cba4b28f97ebdd8ff144e204e204ec~tplv-resize:225:0.image?lk3s=5b7047ff&x-expires=1781853746&x-signature=TATt2UWfG86ME3KdyJ996OaAexY%3D",
          "url": "https://fanqienovel.com/page/7614430898171153433"
        },
        {
          "title": "无限流：摆烂后我封神了",
          "author": "长长长消",
          "reads": "5万",
          "intro": "无cp+系统+迪化流 洛月见一直认为自己是个平凡又普通的人，还有点社恐+面瘫。这样的人扔进人群中毫不起眼，绝对会被所有人忽视掉。 离奇死亡后她被迫进入逃生游戏，她有自知之明，知道自己是绝对没有能力在恐怖逃生游戏中复活的。 就在她纠结到底是要奋力拼一把，还是就此摆烂，突然，她获得了一个完美符合她心意的系统。 摆烂系统：摆烂死亡，直接复活！ 只要宿主在不违规的情况下成功死亡，就可以原地复活，收获1亿现金回到现实世界！ 洛月见邪魅一笑：开摆！ 【恶魔别墅】 洛月见狗狗祟祟的离开房间，欲意作死。 结果，洛月见仿若欧皇附身，随便伸个懒腰，都能避开致命飞箭。 直播间观众震惊：原来是个大佬？！ 洛月见：？ 【死亡沙漠】 洛月见潇洒将自己唯一的水资源倒掉。 下一秒，喝了水的队友B口吐白沫倒地不起。 队友感激涕零：谢大佬提醒！ 洛月见：？ 【长眠地宫】 遍地是毒虫的密道，洛月见直接明演，直接走了进去。 下一秒，毒虫面对洛月见四散奔逃。 队友and观众高呼：不愧是大佬！ 洛月见：？ 面对越来越多的粉丝，以及越来越远的目标。 洛月见笑的狰狞：到底是谁在演我？！",
          "cover": "https://p3-reading-sign.fqnovelpic.com/novel-pic/p2oedac888993929f2c25589afc589c50a4~tplv-resize:225:0.image?lk3s=5b7047ff&x-expires=1781853746&x-signature=ZsdxHtPR%2B5rgHSOp5J9cOjaMOHs%3D",
          "url": "https://fanqienovel.com/page/7197271483859602447"
        },
        {
          "title": "我娇滴滴的，怎么都说我灭诡之神",
          "author": "巢怜云",
          "reads": "4.8万",
          "intro": "【真恐怖游戏+绝对看不见诡异的女主+轻松搞笑】 恐怖游戏降临，人们不仅得面对恐怖的诡异和各种规则，还得面对严重的精神污染，就在人们几乎撑不住时，一个神奇的纸扎铺出现了。 纸扎铺出品，皆是精品。 平安符能瞬间清零所有精神污染。 驱鬼符能瞬杀诡异。 甚至是店里的纸钱，都能驱赶诡异。 … “纸扎铺又上新品了，快抢！” * 马小扁穿越了，穿越到平行时空，从一个贫穷的孤儿，变成一个继承了纸扎铺的贫穷孤儿，身为心理学诈骗预备犯的她，很快发现，这个世界的人相当迷信，嘴里高喊着什么鬼蜮啊，诡异啊，恐怖游戏什么的，就开始拼命砸钱。 迷信好啊，迷信的钱最好赚了！ 她立马开始手动画符纸，诈骗式宣传，高价售卖，一骗一个不吱声。 “小老板，真是太谢谢你了！” 看，他们甚至还要谢谢她。",
          "cover": "https://p3-reading-sign.fqnovelpic.com/novel-pic/p2oe9ac83bf1e508429295167b45d7a983d~tplv-resize:225:0.image?lk3s=5b7047ff&x-expires=1781853746&x-signature=w64M6bkm1jk3cl9S8RrfrMzeh%2Fg%3D",
          "url": "https://fanqienovel.com/page/7501489140878298137"
        },
        {
          "title": "玩家？她是恐怖副本npc哦",
          "author": "岁岁儿",
          "reads": "4.6万",
          "intro": "巫乐是恐怖游戏里面的杀戮npc，在各个副本轮转‘打工’！ 巫乐自由且任性，欺骗玩家，戏耍玩家，恐吓玩家，是她的日常。 　　她时而喜欢假扮玩家，近距离观赏人心险恶，给予玩家希望，最后彻底粉碎，欣赏他们绝望的神情。 　　她时而也会规规矩矩扮演一个合格的恐怖npc，追杀玩家。 　　 　　她喜欢一切漂亮的事物，无聊的时候最爱挑逗自己的那些恐怖npc同事，前提条件是这位npc得够漂亮。 　　反正都是无意识的副本npc,调戏了也不用负责。 　　巫乐想象很美好，直到有一天她发现自己天真了。 　　“巫乐乐，这次为什么不亲我？我这具身体不够漂亮吗？”恐怖boss步步紧逼。 　　········ 　　倒霉的人类被拉入了无限恐怖世界，成为了恐游玩家，他们必须通过一个个副本才能活下去。 　　副本内没有法治可言，充满危机，鬼怪横行，玩家们像蝼蚁一般艰难求生。 　　为了活下去，玩家们学会了踩着同类尸骨，互相欺骗，还有抱老玩家大佬们的大腿！ 　　漂亮诡异的少女，据说是顶级玩家，是公会顶级大佬！ 　　抱到大腿了？ 　　一路惊魂，眼看着离开副本的希望就在眼前，少女化身恶魔:“谁跟你们说我是玩家了？”",
          "cover": "https://p3-reading-sign.fqnovelpic.com/novel-pic/p2oa1b35d36c3b50e2c5cffe409859626ff~tplv-resize:225:0.image?lk3s=5b7047ff&x-expires=1781853746&x-signature=2P300MGYxhojR7fBeFF5JhL%2FjmE%3D",
          "url": "https://fanqienovel.com/page/7389963114571107390"
        },
        {
          "title": "惊悚游戏：我穿越到了童话世界？",
          "author": "火锅涮毛肚",
          "reads": "4.2万",
          "intro": "【暗黑童话+惊悚游戏+直播+爆笑+无cp+非常规结局】 我叫时予，是个精神病人，一觉醒来，被传送进名叫“小红帽”的恐怖游戏。 妈妈的头上正在冒黑气，送给外婆的蛋糕里掺杂了不明种类肉糜…… 游戏情况全球实时直播，人们惊讶的发现： 当其它玩家见到诡异瑟瑟发抖的时候，一个娇小的身影，却早已开始了属于自己的大屠杀…… 游戏一：小红帽 游戏二：灰姑娘 游戏三：拇指姑娘 游戏四：皇帝的新装 游戏五：…… ……",
          "cover": "https://p3-reading-sign.fqnovelpic.com/novel-pic/p2obb90fe216a3e35318fb99c793f5ca9ac~tplv-resize:225:0.image?lk3s=5b7047ff&x-expires=1781853746&x-signature=q7y4c3d7TQkpw1CD9CHkZ5ZuIaw%3D",
          "url": "https://fanqienovel.com/page/7441543479412395032"
        },
        {
          "title": "盗墓：二爷有个反骨崽",
          "author": "鱼aaaaa",
          "reads": "4.1万",
          "intro": "【原创主角+嫩牛五方+All向+主攻+平遗憾】 脑洞大开，新手小白文，主角有点魔丸潜质（大概。。）走剧情 无澈，一个清澈愚蠢的大学生，成了无二白的孩子。 无澈乐疯了，他可以使劲浪了，有人兜底啦，哈哈 无二白也疯了，快让孩子逼疯了。 当初—— 没打算要孩子的无二白突然有了个崽，从此走上了给崽收拾烂摊子的不归路。 而无邪高兴了，因为他终于有兄弟了。以后挨打都有人跟他一起了，高兴的不行。 后来—— “无澈！！”无二白的清静日子一去不复返。 日常深呼吸加河东狮吼。 再后来— 无邪抓狂：“你放下，不准碰！！” 王胖子试图劝架：“咱乖啊，去吃饭，那不能吃！！！熊孩子！！” 黑瞎子崩溃：“那个是真品，很值钱，不能扔！！！” 张麒灵死鱼盯：“不可以！” 谢雨晨掰断了手里的笔：“我让你放下！！” 简介无能，后续还要改。。",
          "cover": "https://p3-reading-sign.fqnovelpic.com/novel-pic/p2o5b38a1f372f84a2cd126e8a7596bf9cb~tplv-resize:225:0.image?lk3s=5b7047ff&x-expires=1781853746&x-signature=%2BLlBDVEL%2BnoG%2BnR7avrp0Wv2NGI%3D",
          "url": "https://fanqienovel.com/page/7613341615322582078"
        },
        {
          "title": "在无限流长的太漂亮是会被亲哭的",
          "author": "美女子牙牙",
          "reads": "3.7万",
          "intro": "［bg+女嬷万人迷+1vn+无限流+女主漂亮娇软可爱+男主阴湿疯批变态坏种+男全洁］ 　 　从小身在有钱家庭却因为身体原因，很少外出的池姝没想到会在自己二十岁生日当天被一个惊悚游戏选中，进入到了无限流世界，成了一名战五渣的新人玩家。 　　没了权势金钱，身娇体软还爱哭的大小姐看着像是连第一关都过不了，但身边突然围上来了一群赶不走的恶犬，一边帮着她过关，一边对着漂亮的大小姐虎视眈眈。 　　直播间的粉丝一开始还在担心这娇气的小美人能活多久，却没想到身娇体软的大小姐靠着一张让神明鬼怪都心软的脸一路过五关斩六将活到了最后。 　　只是副本过着过着，眼看大小姐和身边的恶犬越来越亲密，粉丝笑的越发开心了，当事人却还没意识到事情的严重性，直到有一天池姝被坏男人堵在墙角，亲的不知天地为何物，摁着不让逃走的时候，余光里看见粉丝的一条弹幕，姝姝不知道在无限流长的太漂亮是会被亲哭的吗？ 　　避雷: 　　1.非大女主女强文，万人迷玛丽苏爽文，漂亮娇软怯弱女主，且有时道德感较低，涉及大量女主外貌颜值描写(男性视角大量男凝)存在恶毒女配恶毒男配 详细避雷看第一章૮₍◜ෆ◝.",
          "cover": "https://p3-reading-sign.fqnovelpic.com/novel-pic/2ca73fd4f45b4762b8a18d24cb984e23~tplv-resize:225:0.image?lk3s=5b7047ff&x-expires=1781853746&x-signature=BFz84Lfnf4F2tilQNgPR517H9i4%3D",
          "url": "https://fanqienovel.com/page/7560332930845789209"
        },
        {
          "title": "盗墓：别不拿NPC当回事",
          "author": "泗九七七",
          "reads": "3.7万",
          "intro": "【系统+ooc+搞笑+无CP】（评分刚出会涨） 重生盗墓世界，直接喜提粽子编制！ 花手女傀、全旋血尸、富贵禁婆轮番上线，靠着崩坏拉满的尸系人设，疯狂攒够复活值。 到头来却才发现一切都是假象，榜一大哥吴邪竟成了备选方案。 没关系，只要没活就往死里折腾！ 是向死而生，还是向生赴死？ 我秦安西尸放荡不羁爱自由。",
          "cover": "https://p3-reading-sign.fqnovelpic.com/novel-pic/p2ob4b80af6bb8997f753cc8f035565a7e6~tplv-resize:225:0.image?lk3s=5b7047ff&x-expires=1781853746&x-signature=ptGLdFt5cA4DreaM%2BnABtjQsJ6I%3D",
          "url": "https://fanqienovel.com/page/7619751669747698750"
        },
        {
          "title": "【末世】别睡觉！会死！",
          "author": "步步见喜",
          "reads": "3.7万",
          "intro": "【重生+无限流+女强+无CP+微群像+梦魇入侵】 倒计时随机出现在城市上空，时间清零时，城市居民强制陷入沉睡，被拉入梦魇世界。 黎戈重生后就一个想法，杀光所有诡异种，干死梦魇！ 起初梦魇怪物们以为黎戈只是个好吃的人类罢了，到后来…… 到底谁才是怪物！食物链的顺序是不是错了喂！ 人类世界里，污染侵蚀，长满人嘴的嗜血山茶花、演唱会上诱惑粉丝化蝶献祭的巨星天王，鲜货火锅店现抠人肠来一份？ 黎戈表示，没什么是一锤子解决不了的。 如果解决不了，那就吃掉吧，反正她一直饿得慌。 当梦魇席卷整个世界，不论是人类中的清醒者还是普通人都绝望时，一人带队杀穿梦魇。 人类清醒者论坛曙光APP： ——恭喜【梦魇是个锤子】击杀灭城级诡异种地狱魔章！ ——恭喜【假面】击杀城级诡异种猩红之眼！ “我是黎戈，食梦貘小队队长，曙光ID【梦魇是个锤子】【假面】。” “你也可以称呼我为诡域支配者，或者……” “梦魇之主。”",
          "cover": "https://p3-reading-sign.fqnovelpic.com/novel-pic/p2od86a11765666ebeee2b72ee2aa14442f~tplv-resize:225:0.image?lk3s=5b7047ff&x-expires=1781853746&x-signature=VeMcPRjgw5PKhUIVk1S5J6vZjJ8%3D",
          "url": "https://fanqienovel.com/page/7581888469618658366"
        }
      ]
    }
  ]
}